{
  "hash": "10661ca2b330e755ec7060857a4a53c4",
  "metadata": {
    "deltaPath": [
      0,
      42
    ],
    "activeScriptHash": "6a47bfc5b7667a5df7fe5439ea897b73"
  },
  "delta": {
    "newElement": {
      "selectbox": {
        "id": "$$ID-f72f99c73419da4827903433c446e56d-market",
        "label": "Select the markets you want to explore",
        "default": 0,
        "options": [
          "Will a Republican win Nevada Presidential Election? - Yes \ud83d\udfe2",
          "Will Donald Trump win the popular vote in the 2024 Presidential Election? - Yes \ud83d\udfe2",
          "Which party wins 2024 US Presidential Election? - No \ud83d\udd34",
          "Will Wisconsin be the closest state? - Yes \ud83d\udfe2",
          "Will Jill Stein get the most votes of any 3rd party candidate? - Yes \ud83d\udfe2",
          "Annual inflation above 2.5% in August? - Yes \ud83d\udfe2",
          "GOP wins popular vote by 2-3%? - Yes \ud83d\udfe2",
          "Will the Republican candidate win Pennsylvania by 0%-0.5%? - Yes \ud83d\udfe2",
          "Will RFK Jr. win 1-2% of the popular vote? - Yes \ud83d\udfe2",
          "Will Brazil unban X before October? - Yes \ud83d\udfe2",
          "Will the Republican candidate win Wisconsin by 0%-1.0%? - Yes \ud83d\udfe2",
          "Will the Republican candidate win Georgia by 2.0%-3.0%? - Yes \ud83d\udfe2",
          "If RFK drops out, who will gain more in polls? - No \ud83d\udd34",
          "Bitcoin above $60,000 on October 1? - No \ud83d\udd34",
          "Bitcoin above $55,000 on September 13? - Yes \ud83d\udfe2",
          "Will the Democratic candidate win Michigan by 0%-1.0%? - Yes \ud83d\udfe2",
          "Iran military response before October? - Yes \ud83d\udfe2",
          "Will a Republican win Minnesota in the 2024 US Presidential Election? - Yes \ud83d\udfe2",
          "Will Donald Trump win the 2024 US Presidential Election? - Yes \ud83d\udfe2",
          "Will Trump say alien on The Joe Rogan Experience? - Yes \ud83d\udfe2",
          "Will Trump say FBI on The Joe Rogan Experience? - Yes \ud83d\udfe2",
          "Will Pennsylvania be the closest state? - Yes \ud83d\udfe2",
          "Will Trump x Rogan interview last 120-150 min? - Yes \ud83d\udfe2",
          "Will Trump say Epstein on The Joe Rogan Experience? - Yes \ud83d\udfe2",
          "Will Republicans have 49 or fewer seats in Senate after election? - Yes \ud83d\udfe2",
          "Will Trump win 5 swing states? - Yes \ud83d\udfe2",
          "2024 presidential election: Democrats win by 0-4 - Yes \ud83d\udfe2",
          "Record turnout in 2024 Presidential election? - Yes \ud83d\udfe2",
          "Solana above $170 on November 8? - Yes \ud83d\udfe2",
          "Will a Republican win New Hampshire in the 2024 US Presidential Election? - Yes \ud83d\udfe2",
          "Trump Sun Belt swing state sweep? - Yes \ud83d\udfe2",
          "Will the Republican candidate win Pennsylvania by 0.5%-1.0%? - Yes \ud83d\udfe2",
          "Will Trump x Rogan interview last 150-180 min? - Yes \ud83d\udfe2",
          "GOP wins popular vote by 0-1%? - Yes \ud83d\udfe2",
          "Kamala flips a 2020 Trump state? - No \ud83d\udd34",
          "Will Trump win 30% of Black men? - Yes \ud83d\udfe2",
          "Will Trump x Rogan interview last 90-120 min? - Yes \ud83d\udfe2",
          "Israel strike on Iranian nuclear facility in 2024? - No \ud83d\udd34",
          "Will a Republican win Michigan Presidential Election? - Yes \ud83d\udfe2",
          "Will a Republican win Wisconsin Presidential Election? - Yes \ud83d\udfe2",
          "House control after 2024 election? - No \ud83d\udd34",
          "Will Trump win 7 swing states? - Yes \ud83d\udfe2",
          "Will Michigan be the closest state? - Yes \ud83d\udfe2",
          "Will Kamala get more votes than Biden? - No \ud83d\udd34",
          "Democrats win popular vote by 0-1%? - Yes \ud83d\udfe2",
          "Will Trump do better in Florida or Alaska? - No \ud83d\udd34",
          "Will Trump win Florida by 8+ points? - No \ud83d\udd34",
          "Will Republicans have 50 seats in Senate after election? - Yes \ud83d\udfe2",
          "Will the Republican candidate win North Carolina by 3.0%-4.0%? - Yes \ud83d\udfe2",
          "Will a Republican win North Carolina Presidential Election? - Yes \ud83d\udfe2",
          "Trump gets more black voters than in 2020? - Yes \ud83d\udfe2",
          "Will a Republican win New Mexico Presidential Election? - Yes \ud83d\udfe2",
          "Kamala wins 270-268 - MI, PA, WI - Yes \ud83d\udfe2",
          "Will a Republican win Ohio US Senate Election? - Yes \ud83d\udfe2",
          "Trump wins 287-251 - AZ, GA, NV, NC, PA - Yes \ud83d\udfe2",
          "Will a Republican win the popular vote and the Presidency? - Yes \ud83d\udfe2",
          "Will Republicans have 53 seats in Senate after election? - Yes \ud83d\udfe2",
          "Will Trump win 6 swing states? - Yes \ud83d\udfe2",
          "Will Andr\u00e9 Fernandes win the 2024 Fortaleza mayoral election? - Yes \ud83d\udfe2",
          "Will Joe Rogan announce he is voting for Trump? - Yes \ud83d\udfe2",
          "Will Bitcoin dip to $57,500 in October? - Yes \ud83d\udfe2",
          "Will the Republican candidate win Pennsylvania by 2.0%-2.5%? - Yes \ud83d\udfe2",
          "2024 Balance of Power: R Prez R Senate R House - Yes \ud83d\udfe2",
          "Will Kamala win New York by 10+ points? - No \ud83d\udd34",
          "Will Trump get 82-84m votes in the 2024 U.S. Presidential Election? - Yes \ud83d\udfe2",
          "Will Republicans have 54 seats in Senate after election? - Yes \ud83d\udfe2",
          "Will Bitcoin reach $70,000 in October? - Yes \ud83d\udfe2",
          "Another Iran strike on Israel in October? - No \ud83d\udd34",
          "Will Nevada be the closest state? - Yes \ud83d\udfe2",
          "Will a Republican win Arizona US Senate Election? - Yes \ud83d\udfe2",
          "Will Trump win Iowa by 12+ points? - No \ud83d\udd34",
          "Will Harris win Maine by 5+ points? - No \ud83d\udd34",
          "Will 3rd parties cost Kamala Michigan? - Yes \ud83d\udfe2",
          "2024 presidential election: GOP wins by 35-64 - Yes \ud83d\udfe2",
          "Will a Republican win Virginia Presidential Election? - Yes \ud83d\udfe2",
          "Will a Republican win Pennsylvania Presidential Election? - Yes \ud83d\udfe2",
          "Trump wins every swing state? - Yes \ud83d\udfe2",
          "2024 presidential election: GOP wins by 65-104 - Yes \ud83d\udfe2"
        ],
        "labelVisibility": {},
        "acceptNewOptions": false
      },
      "widthConfig": {
        "useStretch": true
      }
    }
  }
}