{
  "hash": "e16282ace86ab8fd4e8b5072774f4523",
  "metadata": {
    "deltaPath": [
      0,
      42
    ],
    "activeScriptHash": "6a47bfc5b7667a5df7fe5439ea897b73"
  },
  "delta": {
    "newElement": {
      "selectbox": {
        "id": "$$ID-e7af6cd26a423a73841ee1596064809e-market",
        "label": "Select the markets you want to explore",
        "default": 0,
        "options": [
          "Capitals vs. Oilers (2025-01-22 UTC) - Yes \ud83d\udfe2",
          "Panthers vs. Ducks (2025-01-22 UTC) - Yes \ud83d\udfe2",
          "Sharks vs. Predators (2025-01-22 UTC) - No \ud83d\udd34",
          "Sabres vs. Canucks (2025-01-22 UTC) - Yes \ud83d\udfe2",
          "Hawks vs. Jazz (2025-01-08 UTC) - Yes \ud83d\udfe2",
          "Lakers vs. Mavericks (2025-01-08 UTC) - Yes \ud83d\udfe2",
          "Rockets vs. Grizzlies (2025-01-31 UTC) - Yes \ud83d\udfe2",
          "Blue Jackets vs. Golden Knights (2025-01-31 UTC) - Yes \ud83d\udfe2",
          "Wild vs. Canadiens (2025-01-31 UTC) - Yes \ud83d\udfe2",
          "Red Wings vs. Oilers (2025-01-31 UTC) - Yes \ud83d\udfe2",
          "Jets vs. Bruins (2025-01-31 UTC) - No \ud83d\udd34",
          "Blackhawks vs. Hurricanes (2025-01-31 UTC) - Yes \ud83d\udfe2",
          "Kings vs. Lightning (2025-01-31 UTC) - Yes \ud83d\udfe2",
          "Wild vs. Senators (2025-02-02 UTC) - Yes \ud83d\udfe2",
          "Islanders vs. Lightning (2025-02-02 UTC) - No \ud83d\udd34",
          "Jets vs. Capitals (2025-02-02 UTC) - No \ud83d\udd34",
          "Stars vs. Rangers (2025-01-08 UTC) - Yes \ud83d\udfe2",
          "Heat vs. Warriors (2025-01-08 UTC) - No \ud83d\udd34",
          "Hawks vs. Pacers (2025-02-01 UTC) - No \ud83d\udd34",
          "Blackhawks vs. Panthers (2025-02-01 UTC) - No \ud83d\udd34",
          "Rangers vs. Bruins (2025-02-01 UTC) - No \ud83d\udd34",
          "Wizards vs. Timberwolves (2025-02-02 UTC) - No \ud83d\udd34",
          "Devils vs. Penguins (2025-02-05 UTC) - Yes \ud83d\udfe2",
          "Devils vs. Sabres (2025-02-02 UTC) - No \ud83d\udd34",
          "Hurricanes vs. Stars (2025-01-22 UTC) - Yes \ud83d\udfe2",
          "Clippers vs. Nuggets (2025-01-09 UTC) - Yes \ud83d\udfe2",
          "Senators vs. Lightning (2025-02-05 UTC) - No \ud83d\udd34",
          "Will BSW win the most seats in the next German election? - Yes \ud83d\udfe2",
          "Hawks vs. Cavaliers (2025-01-31 UTC) - Yes \ud83d\udfe2",
          "Magic vs. Trail Blazers (2025-01-31 UTC) - No \ud83d\udd34",
          "Capitals vs. Senators (2025-01-31 UTC) - No \ud83d\udd34",
          "Kings vs. Hurricanes (2025-02-02 UTC) - No \ud83d\udd34",
          "Maple Leafs vs. Oilers (2025-02-02 UTC) - No \ud83d\udd34",
          "Red Wings vs. Flames (2025-02-02 UTC) - Yes \ud83d\udfe2",
          "Predators vs. Penguins (2025-02-02 UTC) - Yes \ud83d\udfe2",
          "Will Kanye launch a coin in February? - Yes \ud83d\udfe2",
          "Spurs vs. Hawks (2025-02-06 UTC) - No \ud83d\udd34",
          "Magic vs. Kings (2025-02-06 UTC) - Yes \ud83d\udfe2",
          "Warriors vs. Jazz (2025-02-06 UTC) - Yes \ud83d\udfe2",
          "Bruins vs. Panthers (2025-01-11 UTC) - No \ud83d\udd34",
          "Bulls vs. Pacers (2025-01-09 UTC) - No \ud83d\udd34",
          "Spurs vs. Bucks (2025-01-09 UTC) - No \ud83d\udd34",
          "Ducks vs. Flyers (2025-01-12 UTC) - No \ud83d\udd34",
          "Chargers vs. Texans (2025-01-11 UTC) - Yes \ud83d\udfe2",
          "Will Manchester City win on 2025-01-14? - Yes \ud83d\udfe2",
          "Will Liverpool win on 2025-01-14? - Yes \ud83d\udfe2",
          "Pacers vs. Cavaliers (2025-01-12 UTC) - No \ud83d\udd34",
          "Nuggets vs. Mavericks (2025-01-12 UTC) - Yes \ud83d\udfe2",
          "Will Chelsea win on 2025-01-14? - Yes \ud83d\udfe2",
          "Hornets vs. Suns (2025-01-13 UTC) - No \ud83d\udd34",
          "Lightning vs. Canadiens (2025-02-09 UTC) - Yes \ud83d\udfe2",
          "76ers vs. Bucks (2025-02-09 UTC) - No \ud83d\udd34",
          "Panthers vs. Utah (2025-01-09 UTC) - Yes \ud83d\udfe2",
          "Spurs vs. Lakers (2025-01-12 UTC) - No \ud83d\udd34",
          "Hornets vs. Clippers (2025-01-12 UTC) - No \ud83d\udd34",
          "Utah vs. Capitals (2025-02-09 UTC) - No \ud83d\udd34",
          "Will Ethereum hit $2,600.00 again by March 31? - Yes \ud83d\udfe2",
          "Will Ethereum hit $2,800.00 again by March 31? - Yes \ud83d\udfe2",
          "Will Ethereum reach $3000 in May? - Yes \ud83d\udfe2",
          "Will Ethereum reach $2600 in April? - Yes \ud83d\udfe2",
          "Will Ethereum reach $2400 in April? - Yes \ud83d\udfe2",
          "Will Ethereum reach $2000 in April? - Yes \ud83d\udfe2",
          "Will Ethereum reach $2200 in May? - Yes \ud83d\udfe2",
          "Will Ethereum reach $2600 in May? - Yes \ud83d\udfe2",
          "Will Ethereum reach $2400 in May? - Yes \ud83d\udfe2",
          "Will Ethereum reach $3200 in June? - Yes \ud83d\udfe2",
          "Will Ethereum reach $4000 in June? - Yes \ud83d\udfe2",
          "Will Ethereum reach $2900 in July? - Yes \ud83d\udfe2",
          "Will Ethereum reach $3100 in July? - Yes \ud83d\udfe2",
          "Will Ethereum reach $4200 in August? - Yes \ud83d\udfe2",
          "Will Ethereum reach $4600 in August? - Yes \ud83d\udfe2",
          "Will Aryna Sabalenka win the 2025 US Open? - Yes \ud83d\udfe2",
          "Will Ethereum reach $5400 in September? - Yes \ud83d\udfe2",
          "Will Ethereum reach $5200 in September? - Yes \ud83d\udfe2",
          "Heat vs. Clippers (2025-01-14 UTC) - No \ud83d\udd34",
          "Vikings vs. Rams (2025-01-14 UTC) - Yes \ud83d\udfe2",
          "Warriors vs. Raptors (2025-01-14 UTC) - Yes \ud83d\udfe2",
          "Will Gr\u00fcnen win the most seats in the next German election? - Yes \ud83d\udfe2",
          "Spurs vs. Lakers (2025-01-14 UTC) - No \ud83d\udd34",
          "Will Brentford vs. Liverpool end in a draw? (2025-01-18 UTC) - Yes \ud83d\udfe2",
          "Will Newcastle vs. Bournemouth end in a draw? (2025-01-18 UTC) - Yes \ud83d\udfe2",
          "Will Leicester vs. Fulham end in a draw? (2025-01-18 UTC) - Yes \ud83d\udfe2",
          "Pistons vs. Knicks (2025-01-14 UTC) - No \ud83d\udd34"
        ],
        "labelVisibility": {},
        "acceptNewOptions": false
      },
      "widthConfig": {
        "useStretch": true
      }
    }
  }
}