{
  "hash": "7d2e73aeb5a499854ad8587980903988",
  "metadata": {
    "deltaPath": [
      0,
      4,
      1,
      0
    ],
    "activeScriptHash": "6a47bfc5b7667a5df7fe5439ea897b73"
  },
  "delta": {
    "newElement": {
      "imgs": {
        "imgs": [
          {
            "url": "https://polymarket-upload.s3.us-east-2.amazonaws.com/profile-image-4237779-a69a29a1-91f7-4052-8e3e-1f03f7bace2f.png"
          }
        ]
      },
      "widthConfig": {
        "pixelWidth": 128
      }
    }
  }
}