{
  "hash": "275d798ab865adc09bf60fd1ad251c07",
  "metadata": {
    "deltaPath": [
      0,
      43
    ],
    "activeScriptHash": "6a47bfc5b7667a5df7fe5439ea897b73"
  },
  "delta": {
    "newElement": {
      "selectbox": {
        "id": "$$ID-f957bd358ef346881566243d892f3a3d-market",
        "label": "Select the markets you want to explore",
        "default": 0,
        "options": [
          "Will Johannes Kaiser win the Chilean presidential election? - No \ud83d\udd34",
          "Will Johannes Kaiser win the Chilean presidential election? - Yes \ud83d\udfe2",
          "Bitcoin Up or Down - November 5, 2PM ET - No \ud83d\udd34",
          "Bitcoin Up or Down - November 5, 3PM ET - No \ud83d\udd34",
          "Bitcoin Up or Down - November 5, 3PM ET - Yes \ud83d\udfe2",
          "Bitcoin Up or Down - November 6, 7AM ET - Yes \ud83d\udfe2",
          "Bitcoin Up or Down - November 6, 8AM ET - No \ud83d\udd34",
          "Bitcoin Up or Down - November 6, 9AM ET - Yes \ud83d\udfe2",
          "Bitcoin Up or Down - November 6, 2PM ET - Yes \ud83d\udfe2",
          "Will Jos\u00e9 Antonio Kast win the Chilean presidential election? - Yes \ud83d\udfe2",
          "Will Evelyn Matthei win between 9% and 12% of votes in the first round? - Yes \ud83d\udfe2",
          "Will Evelyn Matthei win between 12% and 15% of votes in the first round? - Yes \ud83d\udfe2",
          "Will Bitcoin dip to $85,000 in November? - Yes \ud83d\udfe2",
          "Will Jeannette Jara win between 24% and 28% of votes in the first round? - Yes \ud83d\udfe2",
          "Bitcoin Up or Down - November 13, 7PM ET - Yes \ud83d\udfe2",
          "Bitcoin Up or Down - November 13, 8PM ET - No \ud83d\udd34",
          "Bitcoin Up or Down - November 13, 9PM ET - No \ud83d\udd34",
          "Bitcoin Up or Down - November 13, 10PM ET - Yes \ud83d\udfe2",
          "Bitcoin Up or Down - November 13, 10PM ET - No \ud83d\udd34",
          "Bitcoin Up or Down on November 14? - Yes \ud83d\udfe2",
          "Bitcoin Up or Down - November 14, 6AM ET - Yes \ud83d\udfe2",
          "Bitcoin Up or Down - November 14, 7AM ET - Yes \ud83d\udfe2",
          "Bitcoin Up or Down - November 18, 8AM ET - Yes \ud83d\udfe2",
          "Will Bitcoin hit $80k or $150k first? - Yes \ud83d\udfe2",
          "Bitcoin Up or Down - November 14, 4:30PM-4:45PM ET - No \ud83d\udd34",
          "Bitcoin Up or Down - November 14, 4:45PM-5:00PM ET - No \ud83d\udd34",
          "Bitcoin Up or Down - November 14, 5:00PM-5:15PM ET - No \ud83d\udd34",
          "Bitcoin Up or Down - November 14, 5:15PM-5:30PM ET - No \ud83d\udd34",
          "Bitcoin Up or Down - November 14, 5:30PM-5:45PM ET - No \ud83d\udd34",
          "Bitcoin Up or Down - November 18, 11:45AM-12:00PM ET - No \ud83d\udd34",
          "Bitcoin Up or Down - November 18, 12:00PM-12:15PM ET - No \ud83d\udd34",
          "Will Jeannette Jara win between 20% and 24% of votes in the first round? - Yes \ud83d\udfe2",
          "Bitcoin Up or Down - November 18, 8:45PM-9:00PM ET - Yes \ud83d\udfe2",
          "Bitcoin Up or Down - November 18, 9:00PM-9:15PM ET - No \ud83d\udd34",
          "Bitcoin Up or Down - November 18, 9:15PM-9:30PM ET - Yes \ud83d\udfe2",
          "Bitcoin Up or Down - November 19, 7:00AM-7:15AM ET - No \ud83d\udd34",
          "Bitcoin Up or Down - November 19, 7:15AM-7:30AM ET - Yes \ud83d\udfe2",
          "Bitcoin Up or Down - November 21, 7:15AM-7:30AM ET - Yes \ud83d\udfe2",
          "Bitcoin Up or Down - November 21, 7AM ET - No \ud83d\udd34",
          "Bitcoin Up or Down - November 21, 5:30PM-5:45PM ET - Yes \ud83d\udfe2",
          "Will Bitcoin dip to $80,000 in November? - Yes \ud83d\udfe2",
          "Will Bitcoin dip to $75,000 in November? - No \ud83d\udd34"
        ],
        "labelVisibility": {},
        "acceptNewOptions": false
      },
      "widthConfig": {
        "useStretch": true
      }
    }
  }
}