{
  "hash": "75dcbd20f589c02166a60a203cfbe9bb",
  "metadata": {
    "activeScriptHash": "3f41e546893dc64b71aaacad12cad815"
  },
  "pageProfile": {
    "commands": [
      {
        "name": "Page",
        "args": [
          {
            "k": "page",
            "t": "function"
          },
          {
            "k": "title",
            "t": "str",
            "m": "len:6"
          },
          {
            "k": "icon",
            "t": "str",
            "m": "len:16"
          }
        ],
        "time": "211"
      },
      {
        "name": "Page",
        "args": [
          {
            "k": "page",
            "t": "function"
          },
          {
            "k": "title",
            "t": "str",
            "m": "len:7"
          },
          {
            "k": "icon",
            "t": "str",
            "m": "len:17"
          }
        ],
        "time": "89"
      },
      {
        "name": "Page",
        "args": [
          {
            "k": "page",
            "t": "str",
            "m": "len:21"
          },
          {
            "k": "title",
            "t": "str",
            "m": "len:12"
          },
          {
            "k": "icon",
            "t": "str",
            "m": "len:26"
          }
        ],
        "time": "470"
      },
      {
        "name": "Page",
        "args": [
          {
            "k": "page",
            "t": "str",
            "m": "len:32"
          },
          {
            "k": "title",
            "t": "str",
            "m": "len:14"
          },
          {
            "k": "icon",
            "t": "str",
            "m": "len:19"
          }
        ],
        "time": "485"
      },
      {
        "name": "Page",
        "args": [
          {
            "k": "page",
            "t": "str",
            "m": "len:26"
          },
          {
            "k": "title",
            "t": "str",
            "m": "len:23"
          },
          {
            "k": "icon",
            "t": "str",
            "m": "len:18"
          }
        ],
        "time": "215"
      },
      {
        "name": "Page",
        "args": [
          {
            "k": "page",
            "t": "str",
            "m": "len:30"
          },
          {
            "k": "title",
            "t": "str",
            "m": "len:12"
          },
          {
            "k": "icon",
            "t": "str",
            "m": "len:17"
          }
        ],
        "time": "290"
      },
      {
        "name": "Page",
        "args": [
          {
            "k": "page",
            "t": "str",
            "m": "len:7"
          },
          {
            "k": "title",
            "t": "str",
            "m": "len:4"
          },
          {
            "k": "icon",
            "t": "str",
            "m": "len:15"
          },
          {
            "k": "default",
            "t": "bool",
            "m": "val:True"
          }
        ],
        "time": "202"
      },
      {
        "name": "Page",
        "args": [
          {
            "k": "page",
            "t": "str",
            "m": "len:22"
          },
          {
            "k": "title",
            "t": "str",
            "m": "len:8"
          },
          {
            "k": "icon",
            "t": "str",
            "m": "len:22"
          }
        ],
        "time": "251"
      },
      {
        "name": "Page",
        "args": [
          {
            "k": "page",
            "t": "str",
            "m": "len:19"
          },
          {
            "k": "title",
            "t": "str",
            "m": "len:12"
          },
          {
            "k": "icon",
            "t": "str",
            "m": "len:15"
          }
        ],
        "time": "358"
      },
      {
        "name": "Page",
        "args": [
          {
            "k": "page",
            "t": "str",
            "m": "len:26"
          },
          {
            "k": "title",
            "t": "str",
            "m": "len:12"
          },
          {
            "k": "icon",
            "t": "str",
            "m": "len:31"
          }
        ],
        "time": "156"
      },
      {
        "name": "Page",
        "args": [
          {
            "k": "page",
            "t": "str",
            "m": "len:35"
          },
          {
            "k": "title",
            "t": "str",
            "m": "len:17"
          },
          {
            "k": "icon",
            "t": "str",
            "m": "len:18"
          },
          {
            "k": "url_path",
            "t": "str",
            "m": "len:17"
          }
        ],
        "time": "136"
      },
      {
        "name": "Page",
        "args": [
          {
            "k": "page",
            "t": "str",
            "m": "len:20"
          },
          {
            "k": "title",
            "t": "str",
            "m": "len:16"
          },
          {
            "k": "icon",
            "t": "str",
            "m": "len:18"
          }
        ],
        "time": "122"
      },
      {
        "name": "Page",
        "args": [
          {
            "k": "page",
            "t": "str",
            "m": "len:26"
          },
          {
            "k": "title",
            "t": "str",
            "m": "len:12"
          },
          {
            "k": "icon",
            "t": "str",
            "m": "len:21"
          }
        ],
        "time": "133"
      },
      {
        "name": "Page",
        "args": [
          {
            "k": "page",
            "t": "str",
            "m": "len:29"
          },
          {
            "k": "title",
            "t": "str",
            "m": "len:15"
          },
          {
            "k": "icon",
            "t": "str",
            "m": "len:23"
          }
        ],
        "time": "125"
      },
      {
        "name": "Page",
        "args": [
          {
            "k": "page",
            "t": "str",
            "m": "len:36"
          },
          {
            "k": "title",
            "t": "str",
            "m": "len:20"
          },
          {
            "k": "icon",
            "t": "str",
            "m": "len:16"
          }
        ],
        "time": "119"
      },
      {
        "name": "Page",
        "args": [
          {
            "k": "page",
            "t": "str",
            "m": "len:20"
          },
          {
            "k": "title",
            "t": "str",
            "m": "len:19"
          },
          {
            "k": "icon",
            "t": "str",
            "m": "len:20"
          }
        ],
        "time": "121"
      },
      {
        "name": "Page",
        "args": [
          {
            "k": "page",
            "t": "str",
            "m": "len:31"
          },
          {
            "k": "title",
            "t": "str",
            "m": "len:12"
          },
          {
            "k": "icon",
            "t": "str",
            "m": "len:14"
          }
        ],
        "time": "119"
      },
      {
        "name": "Page",
        "args": [
          {
            "k": "page",
            "t": "str",
            "m": "len:29"
          },
          {
            "k": "title",
            "t": "str",
            "m": "len:21"
          },
          {
            "k": "icon",
            "t": "str",
            "m": "len:18"
          }
        ],
        "time": "116"
      },
      {
        "name": "Page",
        "args": [
          {
            "k": "page",
            "t": "str",
            "m": "len:22"
          },
          {
            "k": "title",
            "t": "str",
            "m": "len:17"
          },
          {
            "k": "icon",
            "t": "str",
            "m": "len:18"
          }
        ],
        "time": "125"
      },
      {
        "name": "Page",
        "args": [
          {
            "k": "page",
            "t": "str",
            "m": "len:28"
          },
          {
            "k": "title",
            "t": "str",
            "m": "len:14"
          },
          {
            "k": "icon",
            "t": "str",
            "m": "len:31"
          }
        ],
        "time": "118"
      },
      {
        "name": "Page",
        "args": [
          {
            "k": "page",
            "t": "str",
            "m": "len:24"
          },
          {
            "k": "title",
            "t": "str",
            "m": "len:10"
          },
          {
            "k": "icon",
            "t": "str",
            "m": "len:14"
          }
        ],
        "time": "116"
      },
      {
        "name": "Page",
        "args": [
          {
            "k": "page",
            "t": "str",
            "m": "len:29"
          },
          {
            "k": "title",
            "t": "str",
            "m": "len:8"
          },
          {
            "k": "url_path",
            "t": "str",
            "m": "len:15"
          },
          {
            "k": "icon",
            "t": "str",
            "m": "len:22"
          }
        ],
        "time": "148"
      },
      {
        "name": "Page",
        "args": [
          {
            "k": "page",
            "t": "str",
            "m": "len:35"
          },
          {
            "k": "title",
            "t": "str",
            "m": "len:14"
          },
          {
            "k": "url_path",
            "t": "str",
            "m": "len:21"
          },
          {
            "k": "icon",
            "t": "str",
            "m": "len:19"
          }
        ],
        "time": "168"
      },
      {
        "name": "Page",
        "args": [
          {
            "k": "page",
            "t": "str",
            "m": "len:33"
          },
          {
            "k": "title",
            "t": "str",
            "m": "len:12"
          },
          {
            "k": "url_path",
            "t": "str",
            "m": "len:19"
          },
          {
            "k": "icon",
            "t": "str",
            "m": "len:17"
          }
        ],
        "time": "140"
      },
      {
        "name": "Page",
        "args": [
          {
            "k": "page",
            "t": "str",
            "m": "len:32"
          },
          {
            "k": "title",
            "t": "str",
            "m": "len:11"
          },
          {
            "k": "url_path",
            "t": "str",
            "m": "len:18"
          },
          {
            "k": "icon",
            "t": "str",
            "m": "len:23"
          }
        ],
        "time": "168"
      },
      {
        "name": "navigation",
        "args": [
          {
            "k": "pages",
            "t": "dict",
            "m": "len:10"
          },
          {
            "k": "position",
            "t": "str",
            "m": "len:3"
          }
        ],
        "time": "500"
      },
      {
        "name": "set_page_config",
        "args": [
          {
            "k": "page_title",
            "t": "str",
            "m": "len:24"
          },
          {
            "k": "layout",
            "t": "str",
            "m": "len:4"
          },
          {
            "k": "page_icon",
            "t": "str",
            "m": "len:11"
          }
        ],
        "time": "1751"
      },
      {
        "name": "logo",
        "args": [
          {
            "k": "image",
            "t": "str",
            "m": "len:11"
          }
        ],
        "time": "1278"
      },
      {
        "name": "markdown",
        "args": [
          {
            "k": "body",
            "t": "str",
            "m": "len:94",
            "p": 1
          },
          {
            "k": "unsafe_allow_html",
            "t": "bool",
            "m": "val:True"
          }
        ],
        "time": "234"
      },
      {
        "name": "title",
        "args": [
          {
            "k": "body",
            "t": "str",
            "m": "len:24",
            "p": 1
          }
        ],
        "time": "186"
      },
      {
        "name": "context.headers",
        "time": "90"
      },
      {
        "name": "query_params.get_item",
        "args": [
          {
            "k": "key",
            "t": "str",
            "m": "len:6",
            "p": 1
          }
        ]
      },
      {
        "name": "columns",
        "args": [
          {
            "k": "spec",
            "t": "int",
            "p": 1
          }
        ],
        "time": "831"
      },
      {
        "name": "session_state.set_item",
        "args": [
          {
            "k": "key",
            "t": "str",
            "m": "len:12",
            "p": 1
          },
          {
            "k": "value",
            "t": "dict",
            "m": "len:0",
            "p": 2
          }
        ],
        "time": "112"
      },
      {
        "name": "session_state.set_item",
        "args": [
          {
            "k": "key",
            "t": "str",
            "m": "len:14",
            "p": 1
          },
          {
            "k": "value",
            "t": "dict",
            "m": "len:0",
            "p": 2
          }
        ],
        "time": "53"
      },
      {
        "name": "session_state.set_item",
        "args": [
          {
            "k": "key",
            "t": "str",
            "m": "len:16",
            "p": 1
          },
          {
            "k": "value",
            "t": "list",
            "m": "len:0",
            "p": 2
          }
        ],
        "time": "49"
      },
      {
        "name": "query_params.get_all",
        "args": [
          {
            "k": "key",
            "t": "str",
            "m": "len:12",
            "p": 1
          }
        ],
        "time": "57"
      },
      {
        "name": "text_input",
        "args": [
          {
            "k": "label",
            "t": "str",
            "m": "len:52"
          },
          {
            "k": "max_chars",
            "t": "int"
          },
          {
            "k": "key",
            "t": "str",
            "m": "len:12"
          },
          {
            "k": "on_change",
            "t": "function"
          },
          {
            "k": "value",
            "t": "str",
            "m": "len:42"
          }
        ],
        "time": "366"
      },
      {
        "name": "_cache_data_object",
        "args": [
          {
            "k": "key",
            "t": "str",
            "m": "len:32",
            "p": 1
          },
          {
            "k": "value",
            "t": "dict",
            "m": "len:4",
            "p": 2
          },
          {
            "k": "messages",
            "t": "list",
            "m": "len:0",
            "p": 3
          }
        ],
        "time": "291"
      },
      {
        "name": "query_params.set_attr",
        "args": [
          {
            "k": "key",
            "t": "str",
            "m": "len:12",
            "p": 1
          },
          {
            "k": "value",
            "t": "str",
            "m": "len:42",
            "p": 2
          }
        ],
        "time": "251"
      },
      {
        "name": "_cache_data_object",
        "args": [
          {
            "k": "key",
            "t": "str",
            "m": "len:32",
            "p": 1
          },
          {
            "k": "value",
            "t": "dict",
            "m": "len:9",
            "p": 2
          },
          {
            "k": "messages",
            "t": "list",
            "m": "len:0",
            "p": 3
          }
        ],
        "time": "314"
      },
      {
        "name": "image",
        "args": [
          {
            "k": "image",
            "t": "str",
            "m": "len:71",
            "p": 1
          },
          {
            "k": "width",
            "t": "int"
          }
        ],
        "time": "443"
      },
      {
        "name": "caption",
        "args": [
          {
            "k": "body",
            "t": "str",
            "m": "len:8",
            "p": 1
          }
        ],
        "time": "233"
      },
      {
        "name": "divider",
        "time": "380"
      },
      {
        "name": "columns",
        "args": [
          {
            "k": "spec",
            "t": "int",
            "p": 1
          }
        ],
        "time": "3064"
      },
      {
        "name": "badge",
        "args": [
          {
            "k": "label",
            "t": "str",
            "m": "len:10",
            "p": 1
          },
          {
            "k": "icon",
            "t": "str",
            "m": "len:24"
          },
          {
            "k": "color",
            "t": "str",
            "m": "len:4"
          }
        ],
        "time": "643"
      },
      {
        "name": "caption",
        "args": [
          {
            "k": "body",
            "t": "str",
            "m": "len:30",
            "p": 1
          }
        ],
        "time": "252"
      },
      {
        "name": "badge",
        "args": [
          {
            "k": "label",
            "t": "str",
            "m": "len:18",
            "p": 1
          },
          {
            "k": "icon",
            "t": "str",
            "m": "len:17"
          },
          {
            "k": "color",
            "t": "str",
            "m": "len:5"
          }
        ],
        "time": "287"
      },
      {
        "name": "caption",
        "args": [
          {
            "k": "body",
            "t": "str",
            "m": "len:37",
            "p": 1
          }
        ],
        "time": "213"
      },
      {
        "name": "badge",
        "args": [
          {
            "k": "label",
            "t": "str",
            "m": "len:10",
            "p": 1
          },
          {
            "k": "icon",
            "t": "str",
            "m": "len:23"
          },
          {
            "k": "color",
            "t": "str",
            "m": "len:4"
          }
        ],
        "time": "199"
      },
      {
        "name": "caption",
        "args": [
          {
            "k": "body",
            "t": "str",
            "m": "len:20",
            "p": 1
          }
        ],
        "time": "168"
      },
      {
        "name": "divider",
        "time": "161"
      },
      {
        "name": "button",
        "args": [
          {
            "k": "label",
            "t": "str",
            "m": "len:40",
            "p": 1
          }
        ],
        "time": "387"
      },
      {
        "name": "_cache_data_object",
        "args": [
          {
            "k": "key",
            "t": "str",
            "m": "len:32",
            "p": 1
          },
          {
            "k": "value",
            "t": "dict",
            "m": "len:0",
            "p": 2
          },
          {
            "k": "messages",
            "t": "list",
            "m": "len:0",
            "p": 3
          }
        ],
        "time": "277"
      },
      {
        "name": "columns",
        "args": [
          {
            "k": "spec",
            "t": "int",
            "p": 1
          }
        ],
        "time": "1060"
      },
      {
        "name": "markdown",
        "args": [
          {
            "k": "body",
            "t": "str",
            "m": "len:472",
            "p": 1
          },
          {
            "k": "unsafe_allow_html",
            "t": "bool",
            "m": "val:True"
          }
        ],
        "time": "323"
      },
      {
        "name": "empty",
        "time": "363"
      },
      {
        "name": "_cache_data_object",
        "args": [
          {
            "k": "key",
            "t": "str",
            "m": "len:32",
            "p": 1
          },
          {
            "k": "value",
            "t": "float",
            "p": 2
          },
          {
            "k": "messages",
            "t": "list",
            "m": "len:0",
            "p": 3
          }
        ],
        "time": "248"
      },
      {
        "name": "empty",
        "time": "352"
      },
      {
        "name": "markdown",
        "args": [
          {
            "k": "body",
            "t": "str",
            "m": "len:1050",
            "p": 1
          },
          {
            "k": "unsafe_allow_html",
            "t": "bool",
            "m": "val:True"
          }
        ],
        "time": "443"
      },
      {
        "name": "markdown",
        "args": [
          {
            "k": "body",
            "t": "str",
            "m": "len:519",
            "p": 1
          },
          {
            "k": "unsafe_allow_html",
            "t": "bool",
            "m": "val:True"
          }
        ],
        "time": "295"
      },
      {
        "name": "cache_data",
        "args": [
          {
            "k": "func",
            "t": "NoneType"
          },
          {
            "k": "ttl",
            "t": "str",
            "m": "len:2"
          },
          {
            "k": "max_entries",
            "t": "int"
          },
          {
            "k": "persist",
            "t": "NoneType"
          },
          {
            "k": "show_spinner",
            "t": "bool",
            "m": "val:False"
          },
          {
            "k": "show_time",
            "t": "bool",
            "m": "val:False"
          },
          {
            "k": "hash_funcs",
            "t": "NoneType"
          }
        ],
        "time": "130"
      },
      {
        "name": "caption",
        "args": [
          {
            "k": "body",
            "t": "str",
            "m": "len:11",
            "p": 1
          }
        ],
        "time": "282"
      },
      {
        "name": "columns",
        "args": [
          {
            "k": "spec",
            "t": "int",
            "p": 1
          }
        ],
        "time": "644"
      },
      {
        "name": "_cache_data_object",
        "args": [
          {
            "k": "key",
            "t": "str",
            "m": "len:32",
            "p": 1
          },
          {
            "k": "value",
            "t": "requests.models.Response",
            "p": 2
          },
          {
            "k": "messages",
            "t": "list",
            "m": "len:0",
            "p": 3
          }
        ],
        "time": "345"
      },
      {
        "name": "_cache_data_object",
        "args": [
          {
            "k": "key",
            "t": "str",
            "m": "len:32",
            "p": 1
          },
          {
            "k": "value",
            "t": "requests.models.Response",
            "p": 2
          },
          {
            "k": "messages",
            "t": "list",
            "m": "len:0",
            "p": 3
          }
        ],
        "time": "365"
      },
      {
        "name": "_cache_data_object",
        "args": [
          {
            "k": "key",
            "t": "str",
            "m": "len:32",
            "p": 1
          },
          {
            "k": "value",
            "t": "requests.models.Response",
            "p": 2
          },
          {
            "k": "messages",
            "t": "list",
            "m": "len:0",
            "p": 3
          }
        ],
        "time": "370"
      },
      {
        "name": "_cache_data_object",
        "args": [
          {
            "k": "key",
            "t": "str",
            "m": "len:32",
            "p": 1
          },
          {
            "k": "value",
            "t": "requests.models.Response",
            "p": 2
          },
          {
            "k": "messages",
            "t": "list",
            "m": "len:0",
            "p": 3
          }
        ],
        "time": "343"
      },
      {
        "name": "markdown",
        "args": [
          {
            "k": "body",
            "t": "str",
            "m": "len:424",
            "p": 1
          },
          {
            "k": "unsafe_allow_html",
            "t": "bool",
            "m": "val:True"
          }
        ],
        "time": "433"
      },
      {
        "name": "caption",
        "args": [
          {
            "k": "body",
            "t": "str",
            "m": "len:178",
            "p": 1
          }
        ],
        "time": "227"
      },
      {
        "name": "divider",
        "time": "152"
      },
      {
        "name": "cache_data",
        "args": [
          {
            "k": "func",
            "t": "NoneType"
          },
          {
            "k": "ttl",
            "t": "str",
            "m": "len:2"
          },
          {
            "k": "max_entries",
            "t": "int"
          },
          {
            "k": "persist",
            "t": "NoneType"
          },
          {
            "k": "show_spinner",
            "t": "bool",
            "m": "val:False"
          },
          {
            "k": "show_time",
            "t": "bool",
            "m": "val:False"
          },
          {
            "k": "hash_funcs",
            "t": "NoneType"
          }
        ],
        "time": "228"
      },
      {
        "name": "empty",
        "time": "309"
      },
      {
        "name": "empty",
        "time": "340"
      },
      {
        "name": "empty",
        "time": "199"
      },
      {
        "name": "empty",
        "time": "173"
      },
      {
        "name": "_cache_data_object",
        "args": [
          {
            "k": "key",
            "t": "str",
            "m": "len:32",
            "p": 1
          },
          {
            "k": "value",
            "t": "DataFrame",
            "m": "len:82",
            "p": 2
          },
          {
            "k": "messages",
            "t": "list",
            "m": "len:0",
            "p": 3
          }
        ],
        "time": "475"
      },
      {
        "name": "empty",
        "time": "307"
      },
      {
        "name": "_cache_data_object",
        "args": [
          {
            "k": "key",
            "t": "str",
            "m": "len:32",
            "p": 1
          },
          {
            "k": "value",
            "t": "float",
            "p": 2
          },
          {
            "k": "messages",
            "t": "list",
            "m": "len:0",
            "p": 3
          }
        ],
        "time": "266"
      },
      {
        "name": "cache_data",
        "args": [
          {
            "k": "func",
            "t": "NoneType"
          },
          {
            "k": "ttl",
            "t": "int"
          },
          {
            "k": "max_entries",
            "t": "int"
          },
          {
            "k": "persist",
            "t": "NoneType"
          },
          {
            "k": "show_spinner",
            "t": "bool",
            "m": "val:False"
          },
          {
            "k": "show_time",
            "t": "bool",
            "m": "val:False"
          },
          {
            "k": "hash_funcs",
            "t": "NoneType"
          }
        ],
        "time": "143"
      },
      {
        "name": "_cache_data_object",
        "args": [
          {
            "k": "key",
            "t": "str",
            "m": "len:32",
            "p": 1
          },
          {
            "k": "value",
            "t": "str",
            "m": "len:962",
            "p": 2
          },
          {
            "k": "messages",
            "t": "list",
            "m": "len:0",
            "p": 3
          }
        ],
        "time": "263"
      },
      {
        "name": "markdown",
        "args": [
          {
            "k": "body",
            "t": "str",
            "m": "len:962",
            "p": 1
          },
          {
            "k": "unsafe_allow_html",
            "t": "bool",
            "m": "val:True"
          }
        ],
        "time": "584"
      },
      {
        "name": "cache_data",
        "args": [
          {
            "k": "func",
            "t": "NoneType"
          },
          {
            "k": "ttl",
            "t": "int"
          },
          {
            "k": "max_entries",
            "t": "int"
          },
          {
            "k": "persist",
            "t": "NoneType"
          },
          {
            "k": "show_spinner",
            "t": "bool",
            "m": "val:True"
          },
          {
            "k": "show_time",
            "t": "bool",
            "m": "val:False"
          },
          {
            "k": "hash_funcs",
            "t": "NoneType"
          }
        ],
        "time": "148"
      },
      {
        "name": "empty",
        "time": "253"
      },
      {
        "name": "_cache_data_object",
        "args": [
          {
            "k": "key",
            "t": "str",
            "m": "len:32",
            "p": 1
          },
          {
            "k": "value",
            "t": "DataFrame",
            "m": "len:1",
            "p": 2
          },
          {
            "k": "messages",
            "t": "list",
            "m": "len:0",
            "p": 3
          }
        ],
        "time": "293"
      },
      {
        "name": "empty",
        "time": "269"
      },
      {
        "name": "empty",
        "time": "244"
      },
      {
        "name": "_cache_data_object",
        "args": [
          {
            "k": "key",
            "t": "str",
            "m": "len:32",
            "p": 1
          },
          {
            "k": "value",
            "t": "tuple",
            "m": "len:2",
            "p": 2
          },
          {
            "k": "messages",
            "t": "list",
            "m": "len:0",
            "p": 3
          }
        ],
        "time": "6827"
      },
      {
        "name": "empty",
        "time": "425"
      },
      {
        "name": "plotly_chart",
        "args": [
          {
            "k": "figure_or_data",
            "t": "PlotlyFigure",
            "p": 1
          }
        ],
        "time": "9218"
      },
      {
        "name": "markdown",
        "args": [
          {
            "k": "body",
            "t": "str",
            "m": "len:1837",
            "p": 1
          },
          {
            "k": "unsafe_allow_html",
            "t": "bool",
            "m": "val:True"
          }
        ],
        "time": "508"
      },
      {
        "name": "cache_data",
        "args": [
          {
            "k": "func",
            "t": "NoneType"
          },
          {
            "k": "ttl",
            "t": "int"
          },
          {
            "k": "max_entries",
            "t": "int"
          },
          {
            "k": "persist",
            "t": "NoneType"
          },
          {
            "k": "show_spinner",
            "t": "bool",
            "m": "val:False"
          },
          {
            "k": "show_time",
            "t": "bool",
            "m": "val:False"
          },
          {
            "k": "hash_funcs",
            "t": "NoneType"
          }
        ],
        "time": "132"
      },
      {
        "name": "markdown",
        "args": [
          {
            "k": "body",
            "t": "str",
            "m": "len:0",
            "p": 1
          }
        ],
        "time": "561"
      },
      {
        "name": "metric",
        "args": [
          {
            "k": "label",
            "t": "str",
            "m": "len:35"
          },
          {
            "k": "value",
            "t": "str",
            "m": "len:2"
          },
          {
            "k": "chart_data",
            "t": "list",
            "m": "len:30"
          },
          {
            "k": "chart_type",
            "t": "str",
            "m": "len:4"
          }
        ],
        "time": "514"
      },
      {
        "name": "markdown",
        "args": [
          {
            "k": "body",
            "t": "str",
            "m": "len:0",
            "p": 1
          }
        ],
        "time": "246"
      },
      {
        "name": "_cache_data_object",
        "args": [
          {
            "k": "key",
            "t": "str",
            "m": "len:32",
            "p": 1
          },
          {
            "k": "value",
            "t": "NoneType",
            "p": 2
          },
          {
            "k": "messages",
            "t": "list",
            "m": "len:3",
            "p": 3
          }
        ],
        "time": "196"
      },
      {
        "name": "columns",
        "args": [
          {
            "k": "spec",
            "t": "int",
            "p": 1
          }
        ],
        "time": "689"
      },
      {
        "name": "markdown",
        "args": [
          {
            "k": "body",
            "t": "str",
            "m": "len:506",
            "p": 1
          },
          {
            "k": "unsafe_allow_html",
            "t": "bool",
            "m": "val:True"
          }
        ],
        "time": "297"
      },
      {
        "name": "column_config.NumberColumn",
        "args": [
          {
            "k": "label",
            "t": "str",
            "m": "len:12"
          },
          {
            "k": "format",
            "t": "str",
            "m": "len:6"
          },
          {
            "k": "help",
            "t": "str",
            "m": "len:81"
          }
        ],
        "time": "133"
      },
      {
        "name": "column_config.NumberColumn",
        "args": [
          {
            "k": "label",
            "t": "str",
            "m": "len:14"
          },
          {
            "k": "format",
            "t": "str",
            "m": "len:6"
          },
          {
            "k": "help",
            "t": "str",
            "m": "len:75"
          }
        ],
        "time": "83"
      },
      {
        "name": "column_config.NumberColumn",
        "args": [
          {
            "k": "label",
            "t": "str",
            "m": "len:11"
          },
          {
            "k": "format",
            "t": "str",
            "m": "len:6"
          },
          {
            "k": "help",
            "t": "str",
            "m": "len:73"
          }
        ],
        "time": "70"
      },
      {
        "name": "column_config.NumberColumn",
        "args": [
          {
            "k": "label",
            "t": "str",
            "m": "len:13"
          },
          {
            "k": "format",
            "t": "str",
            "m": "len:6"
          },
          {
            "k": "help",
            "t": "str",
            "m": "len:55"
          }
        ],
        "time": "73"
      },
      {
        "name": "column_config.NumberColumn",
        "args": [
          {
            "k": "label",
            "t": "str",
            "m": "len:13"
          },
          {
            "k": "format",
            "t": "str",
            "m": "len:6"
          },
          {
            "k": "help",
            "t": "str",
            "m": "len:31"
          }
        ],
        "time": "67"
      },
      {
        "name": "column_config.NumberColumn",
        "args": [
          {
            "k": "label",
            "t": "str",
            "m": "len:15"
          },
          {
            "k": "help",
            "t": "str",
            "m": "len:47"
          }
        ],
        "time": "57"
      },
      {
        "name": "column_config.NumberColumn",
        "args": [
          {
            "k": "label",
            "t": "str",
            "m": "len:15"
          },
          {
            "k": "format",
            "t": "str",
            "m": "len:7"
          },
          {
            "k": "help",
            "t": "str",
            "m": "len:52"
          }
        ],
        "time": "62"
      },
      {
        "name": "column_config.NumberColumn",
        "args": [
          {
            "k": "label",
            "t": "str",
            "m": "len:14"
          },
          {
            "k": "format",
            "t": "str",
            "m": "len:6"
          },
          {
            "k": "help",
            "t": "str",
            "m": "len:44"
          }
        ],
        "time": "64"
      },
      {
        "name": "column_config.NumberColumn",
        "args": [
          {
            "k": "label",
            "t": "str",
            "m": "len:8"
          },
          {
            "k": "format",
            "t": "str",
            "m": "len:6"
          },
          {
            "k": "help",
            "t": "str",
            "m": "len:56"
          }
        ],
        "time": "60"
      },
      {
        "name": "data_editor",
        "args": [
          {
            "k": "data",
            "t": "PandasStyler",
            "p": 1
          },
          {
            "k": "use_container_width",
            "t": "bool",
            "m": "val:True"
          },
          {
            "k": "hide_index",
            "t": "bool",
            "m": "val:True"
          },
          {
            "k": "disabled",
            "t": "bool",
            "m": "val:True"
          },
          {
            "k": "key",
            "t": "str",
            "m": "len:6"
          },
          {
            "k": "column_config",
            "t": "dict",
            "m": "len:9"
          },
          {
            "k": "column_order",
            "t": "list",
            "m": "len:9"
          }
        ],
        "time": "9656"
      },
      {
        "name": "markdown",
        "args": [
          {
            "k": "body",
            "t": "str",
            "m": "len:510",
            "p": 1
          },
          {
            "k": "unsafe_allow_html",
            "t": "bool",
            "m": "val:True"
          }
        ],
        "time": "394"
      },
      {
        "name": "data_editor",
        "args": [
          {
            "k": "data",
            "t": "PandasStyler",
            "p": 1
          },
          {
            "k": "use_container_width",
            "t": "bool",
            "m": "val:True"
          },
          {
            "k": "hide_index",
            "t": "bool",
            "m": "val:True"
          },
          {
            "k": "disabled",
            "t": "bool",
            "m": "val:True"
          },
          {
            "k": "key",
            "t": "str",
            "m": "len:8"
          },
          {
            "k": "column_config",
            "t": "dict",
            "m": "len:9"
          },
          {
            "k": "column_order",
            "t": "list",
            "m": "len:8"
          }
        ],
        "time": "30927"
      },
      {
        "name": "markdown",
        "args": [
          {
            "k": "body",
            "t": "str",
            "m": "len:1126",
            "p": 1
          },
          {
            "k": "unsafe_allow_html",
            "t": "bool",
            "m": "val:True"
          }
        ],
        "time": "522"
      },
      {
        "name": "markdown",
        "args": [
          {
            "k": "body",
            "t": "str",
            "m": "len:1213",
            "p": 1
          },
          {
            "k": "unsafe_allow_html",
            "t": "bool",
            "m": "val:True"
          }
        ],
        "time": "368"
      },
      {
        "name": "markdown",
        "args": [
          {
            "k": "body",
            "t": "str",
            "m": "len:0",
            "p": 1
          }
        ],
        "time": "247"
      },
      {
        "name": "subheader",
        "args": [
          {
            "k": "body",
            "t": "str",
            "m": "len:24",
            "p": 1
          }
        ],
        "time": "246"
      },
      {
        "name": "caption",
        "args": [
          {
            "k": "body",
            "t": "str",
            "m": "len:133",
            "p": 1
          }
        ],
        "time": "184"
      },
      {
        "name": "plotly_chart",
        "args": [
          {
            "k": "figure_or_data",
            "t": "PlotlyFigure",
            "p": 1
          },
          {
            "k": "use_container_width",
            "t": "bool",
            "m": "val:True"
          }
        ],
        "time": "14103"
      },
      {
        "name": "plotly_chart",
        "args": [
          {
            "k": "figure_or_data",
            "t": "PlotlyFigure",
            "p": 1
          }
        ],
        "time": "1612"
      },
      {
        "name": "columns",
        "args": [
          {
            "k": "spec",
            "t": "int",
            "p": 1
          }
        ],
        "time": "544"
      },
      {
        "name": "subheader",
        "args": [
          {
            "k": "body",
            "t": "str",
            "m": "len:34",
            "p": 1
          }
        ],
        "time": "365"
      },
      {
        "name": "plotly_chart",
        "args": [
          {
            "k": "figure_or_data",
            "t": "PlotlyFigure",
            "p": 1
          },
          {
            "k": "use_container_width",
            "t": "bool",
            "m": "val:True"
          }
        ],
        "time": "1179"
      },
      {
        "name": "subheader",
        "args": [
          {
            "k": "body",
            "t": "str",
            "m": "len:32",
            "p": 1
          }
        ],
        "time": "332"
      },
      {
        "name": "plotly_chart",
        "args": [
          {
            "k": "figure_or_data",
            "t": "PlotlyFigure",
            "p": 1
          },
          {
            "k": "use_container_width",
            "t": "bool",
            "m": "val:True"
          }
        ],
        "time": "1177"
      },
      {
        "name": "cache_data",
        "args": [
          {
            "k": "func",
            "t": "NoneType"
          },
          {
            "k": "ttl",
            "t": "int"
          },
          {
            "k": "max_entries",
            "t": "int"
          },
          {
            "k": "persist",
            "t": "NoneType"
          },
          {
            "k": "show_spinner",
            "t": "str",
            "m": "len:21"
          },
          {
            "k": "show_time",
            "t": "bool",
            "m": "val:False"
          },
          {
            "k": "hash_funcs",
            "t": "NoneType"
          }
        ],
        "time": "129"
      },
      {
        "name": "cache_data",
        "args": [
          {
            "k": "func",
            "t": "NoneType"
          },
          {
            "k": "ttl",
            "t": "int"
          },
          {
            "k": "max_entries",
            "t": "int"
          },
          {
            "k": "persist",
            "t": "NoneType"
          },
          {
            "k": "show_spinner",
            "t": "str",
            "m": "len:29"
          },
          {
            "k": "show_time",
            "t": "bool",
            "m": "val:False"
          },
          {
            "k": "hash_funcs",
            "t": "NoneType"
          }
        ],
        "time": "113"
      },
      {
        "name": "empty",
        "time": "187"
      },
      {
        "name": "_cache_data_object",
        "args": [
          {
            "k": "key",
            "t": "str",
            "m": "len:32",
            "p": 1
          },
          {
            "k": "value",
            "t": "DataFrame",
            "m": "len:1",
            "p": 2
          },
          {
            "k": "messages",
            "t": "list",
            "m": "len:0",
            "p": 3
          }
        ],
        "time": "387"
      },
      {
        "name": "empty",
        "time": "388"
      },
      {
        "name": "empty",
        "time": "240"
      },
      {
        "name": "_cache_data_object",
        "args": [
          {
            "k": "key",
            "t": "str",
            "m": "len:32",
            "p": 1
          },
          {
            "k": "value",
            "t": "DataFrame",
            "m": "len:1",
            "p": 2
          },
          {
            "k": "messages",
            "t": "list",
            "m": "len:0",
            "p": 3
          }
        ],
        "time": "349"
      },
      {
        "name": "empty",
        "time": "780"
      },
      {
        "name": "columns",
        "args": [
          {
            "k": "spec",
            "t": "int",
            "p": 1
          }
        ],
        "time": "741"
      },
      {
        "name": "subheader",
        "args": [
          {
            "k": "body",
            "t": "str",
            "m": "len:22",
            "p": 1
          }
        ],
        "time": "251"
      },
      {
        "name": "plotly_chart",
        "args": [
          {
            "k": "figure_or_data",
            "t": "PlotlyFigure",
            "p": 1
          },
          {
            "k": "use_container_width",
            "t": "bool",
            "m": "val:True"
          }
        ],
        "time": "1423"
      },
      {
        "name": "subheader",
        "args": [
          {
            "k": "body",
            "t": "str",
            "m": "len:23",
            "p": 1
          }
        ],
        "time": "314"
      },
      {
        "name": "markdown",
        "args": [
          {
            "k": "body",
            "t": "str",
            "m": "len:595",
            "p": 1
          },
          {
            "k": "unsafe_allow_html",
            "t": "bool",
            "m": "val:True"
          }
        ],
        "time": "490"
      },
      {
        "name": "plotly_chart",
        "args": [
          {
            "k": "figure_or_data",
            "t": "PlotlyFigure",
            "p": 1
          },
          {
            "k": "use_container_width",
            "t": "bool",
            "m": "val:True"
          }
        ],
        "time": "1188"
      },
      {
        "name": "subheader",
        "args": [
          {
            "k": "body",
            "t": "str",
            "m": "len:20",
            "p": 1
          }
        ],
        "time": "272"
      },
      {
        "name": "plotly_chart",
        "args": [
          {
            "k": "figure_or_data",
            "t": "PlotlyFigure",
            "p": 1
          },
          {
            "k": "use_container_width",
            "t": "bool",
            "m": "val:True"
          }
        ],
        "time": "1408"
      },
      {
        "name": "subheader",
        "args": [
          {
            "k": "body",
            "t": "str",
            "m": "len:57",
            "p": 1
          }
        ],
        "time": "248"
      },
      {
        "name": "query_params.get_item",
        "args": [
          {
            "k": "key",
            "t": "str",
            "m": "len:6",
            "p": 1
          }
        ]
      },
      {
        "name": "query_params.set_item",
        "args": [
          {
            "k": "key",
            "t": "str",
            "m": "len:6",
            "p": 1
          },
          {
            "k": "value",
            "t": "str",
            "m": "len:70",
            "p": 2
          }
        ],
        "time": "171"
      },
      {
        "name": "query_params.get_all",
        "args": [
          {
            "k": "key",
            "t": "str",
            "m": "len:6",
            "p": 1
          }
        ],
        "time": "62"
      },
      {
        "name": "selectbox",
        "args": [
          {
            "k": "label",
            "t": "str",
            "m": "len:38"
          },
          {
            "k": "options",
            "t": "list",
            "m": "len:82"
          },
          {
            "k": "key",
            "t": "str",
            "m": "len:6"
          },
          {
            "k": "on_change",
            "t": "function"
          },
          {
            "k": "index",
            "t": "int"
          }
        ],
        "time": "635"
      },
      {
        "name": "empty",
        "time": "258"
      },
      {
        "name": "_cache_data_object",
        "args": [
          {
            "k": "key",
            "t": "str",
            "m": "len:32",
            "p": 1
          },
          {
            "k": "value",
            "t": "list",
            "m": "len:2",
            "p": 2
          },
          {
            "k": "messages",
            "t": "list",
            "m": "len:3",
            "p": 3
          }
        ],
        "time": "281"
      },
      {
        "name": "empty",
        "time": "562"
      },
      {
        "name": "_cache_data_object",
        "args": [
          {
            "k": "key",
            "t": "str",
            "m": "len:32",
            "p": 1
          },
          {
            "k": "value",
            "t": "dict",
            "m": "len:1",
            "p": 2
          },
          {
            "k": "messages",
            "t": "list",
            "m": "len:0",
            "p": 3
          }
        ],
        "time": "257"
      },
      {
        "name": "empty",
        "time": "270"
      },
      {
        "name": "empty",
        "time": "204"
      },
      {
        "name": "_cache_data_object",
        "args": [
          {
            "k": "key",
            "t": "str",
            "m": "len:32",
            "p": 1
          },
          {
            "k": "value",
            "t": "list",
            "m": "len:1",
            "p": 2
          },
          {
            "k": "messages",
            "t": "list",
            "m": "len:3",
            "p": 3
          }
        ],
        "time": "263"
      },
      {
        "name": "_cache_data_object",
        "args": [
          {
            "k": "key",
            "t": "str",
            "m": "len:32",
            "p": 1
          },
          {
            "k": "value",
            "t": "dict",
            "m": "len:4",
            "p": 2
          },
          {
            "k": "messages",
            "t": "list",
            "m": "len:0",
            "p": 3
          }
        ],
        "time": "162"
      },
      {
        "name": "warning",
        "args": [
          {
            "k": "body",
            "t": "str",
            "m": "len:76",
            "p": 1
          }
        ],
        "time": "439"
      },
      {
        "name": "plotly_chart",
        "args": [
          {
            "k": "figure_or_data",
            "t": "PlotlyFigure",
            "p": 1
          }
        ],
        "time": "1928"
      },
      {
        "name": "plotly_chart",
        "args": [
          {
            "k": "figure_or_data",
            "t": "PlotlyFigure",
            "p": 1
          },
          {
            "k": "use_container_width",
            "t": "bool",
            "m": "val:True"
          }
        ],
        "time": "2218"
      },
      {
        "name": "cache_data",
        "args": [
          {
            "k": "func",
            "t": "NoneType"
          },
          {
            "k": "ttl",
            "t": "int"
          },
          {
            "k": "max_entries",
            "t": "int"
          },
          {
            "k": "persist",
            "t": "NoneType"
          },
          {
            "k": "show_spinner",
            "t": "str",
            "m": "len:21"
          },
          {
            "k": "show_time",
            "t": "bool",
            "m": "val:False"
          },
          {
            "k": "hash_funcs",
            "t": "NoneType"
          }
        ],
        "time": "300"
      },
      {
        "name": "empty",
        "time": "425"
      },
      {
        "name": "_cache_data_object",
        "args": [
          {
            "k": "key",
            "t": "str",
            "m": "len:32",
            "p": 1
          },
          {
            "k": "value",
            "t": "DataFrame",
            "m": "len:50",
            "p": 2
          },
          {
            "k": "messages",
            "t": "list",
            "m": "len:0",
            "p": 3
          }
        ],
        "time": "464"
      },
      {
        "name": "empty",
        "time": "308"
      },
      {
        "name": "subheader",
        "args": [
          {
            "k": "body",
            "t": "str",
            "m": "len:13",
            "p": 1
          }
        ],
        "time": "330"
      },
      {
        "name": "column_config.DatetimeColumn",
        "args": [
          {
            "k": "label",
            "t": "str",
            "m": "len:9"
          },
          {
            "k": "format",
            "t": "str",
            "m": "len:16"
          }
        ],
        "time": "112"
      },
      {
        "name": "column_config.TextColumn",
        "args": [
          {
            "k": "label",
            "t": "str",
            "m": "len:8"
          },
          {
            "k": "required",
            "t": "bool",
            "m": "val:False"
          },
          {
            "k": "help",
            "t": "str",
            "m": "len:29"
          }
        ],
        "time": "76"
      },
      {
        "name": "column_config.TextColumn",
        "args": [
          {
            "k": "label",
            "t": "str",
            "m": "len:4"
          },
          {
            "k": "help",
            "t": "str",
            "m": "len:29"
          }
        ],
        "time": "57"
      },
      {
        "name": "column_config.NumberColumn",
        "args": [
          {
            "k": "label",
            "t": "str",
            "m": "len:5"
          },
          {
            "k": "format",
            "t": "str",
            "m": "len:6"
          }
        ],
        "time": "63"
      },
      {
        "name": "column_config.NumberColumn",
        "args": [
          {
            "k": "label",
            "t": "str",
            "m": "len:10"
          },
          {
            "k": "format",
            "t": "str",
            "m": "len:6"
          }
        ],
        "time": "59"
      },
      {
        "name": "column_config.NumberColumn",
        "args": [
          {
            "k": "label",
            "t": "str",
            "m": "len:6"
          },
          {
            "k": "format",
            "t": "str",
            "m": "len:4"
          }
        ],
        "time": "64"
      },
      {
        "name": "column_config.TextColumn",
        "args": [
          {
            "k": "label",
            "t": "str",
            "m": "len:7"
          },
          {
            "k": "help",
            "t": "str",
            "m": "len:49"
          }
        ],
        "time": "57"
      },
      {
        "name": "data_editor",
        "args": [
          {
            "k": "data",
            "t": "PandasStyler",
            "p": 1
          },
          {
            "k": "hide_index",
            "t": "bool",
            "m": "val:True"
          },
          {
            "k": "use_container_width",
            "t": "bool",
            "m": "val:True"
          },
          {
            "k": "column_config",
            "t": "dict",
            "m": "len:7"
          },
          {
            "k": "column_order",
            "t": "list",
            "m": "len:7"
          },
          {
            "k": "disabled",
            "t": "bool",
            "m": "val:True"
          }
        ],
        "time": "17183"
      },
      {
        "name": "cache_data",
        "args": [
          {
            "k": "func",
            "t": "NoneType"
          },
          {
            "k": "ttl",
            "t": "int"
          },
          {
            "k": "max_entries",
            "t": "int"
          },
          {
            "k": "persist",
            "t": "NoneType"
          },
          {
            "k": "show_spinner",
            "t": "str",
            "m": "len:24"
          },
          {
            "k": "show_time",
            "t": "bool",
            "m": "val:False"
          },
          {
            "k": "hash_funcs",
            "t": "NoneType"
          }
        ],
        "time": "152"
      },
      {
        "name": "empty",
        "time": "201"
      },
      {
        "name": "_cache_data_object",
        "args": [
          {
            "k": "key",
            "t": "str",
            "m": "len:32",
            "p": 1
          },
          {
            "k": "value",
            "t": "DataFrame",
            "m": "len:7",
            "p": 2
          },
          {
            "k": "messages",
            "t": "list",
            "m": "len:0",
            "p": 3
          }
        ],
        "time": "249"
      },
      {
        "name": "empty",
        "time": "187"
      },
      {
        "name": "markdown",
        "args": [
          {
            "k": "body",
            "t": "str",
            "m": "len:4",
            "p": 1
          },
          {
            "k": "unsafe_allow_html",
            "t": "bool",
            "m": "val:True"
          }
        ],
        "time": "318"
      },
      {
        "name": "plotly_chart",
        "args": [
          {
            "k": "figure_or_data",
            "t": "PlotlyFigure",
            "p": 1
          },
          {
            "k": "use_container_width",
            "t": "bool",
            "m": "val:True"
          }
        ],
        "time": "1057"
      },
      {
        "name": "expander",
        "args": [
          {
            "k": "label",
            "t": "str",
            "m": "len:12",
            "p": 1
          }
        ],
        "time": "201"
      },
      {
        "name": "form",
        "args": [
          {
            "k": "key",
            "t": "str",
            "m": "len:12",
            "p": 1
          }
        ],
        "time": "179"
      },
      {
        "name": "text_input",
        "args": [
          {
            "k": "label",
            "t": "str",
            "m": "len:72",
            "p": 1
          }
        ],
        "time": "314"
      },
      {
        "name": "form_submit_button",
        "args": [
          {
            "k": "label",
            "t": "str",
            "m": "len:6",
            "p": 1
          }
        ],
        "time": "243"
      },
      {
        "name": "divider",
        "time": "153"
      },
      {
        "name": "write",
        "args": [
          {
            "k": "1",
            "t": "str",
            "m": "len:104",
            "p": 1
          }
        ],
        "time": "228"
      }
    ],
    "execTime": "10449373",
    "prepTime": "769",
    "config": [
      "client.showErrorDetails",
      "theme.base",
      "theme.backgroundColor",
      "theme.dataframeHeaderBackgroundColor",
      "global.showWarningOnDirectExecution",
      "server.port:default",
      "client.toolbarMode",
      "server.address",
      "theme.textColor",
      "theme.font",
      "ui.hideTopBar",
      "theme.primaryColor",
      "theme.secondaryBackgroundColor"
    ],
    "attributions": [
      "psycopg2",
      "authlib",
      "pydantic",
      "pymongo",
      "sqlite3",
      "streamlit_extras"
    ],
    "os": "linux",
    "timezone": "('UTC', 'UTC')",
    "headless": true
  }
}