{
  "hash": "996427c56972a4caf3502bf6f0436cc5",
  "metadata": {
    "activeScriptHash": "3f41e546893dc64b71aaacad12cad815"
  },
  "pageProfile": {
    "commands": [
      {
        "name": "Page",
        "args": [
          {
            "k": "page",
            "t": "function"
          },
          {
            "k": "title",
            "t": "str",
            "m": "len:6"
          },
          {
            "k": "icon",
            "t": "str",
            "m": "len:16"
          }
        ],
        "time": "209"
      },
      {
        "name": "Page",
        "args": [
          {
            "k": "page",
            "t": "function"
          },
          {
            "k": "title",
            "t": "str",
            "m": "len:7"
          },
          {
            "k": "icon",
            "t": "str",
            "m": "len:17"
          }
        ],
        "time": "85"
      },
      {
        "name": "Page",
        "args": [
          {
            "k": "page",
            "t": "str",
            "m": "len:21"
          },
          {
            "k": "title",
            "t": "str",
            "m": "len:12"
          },
          {
            "k": "icon",
            "t": "str",
            "m": "len:26"
          }
        ],
        "time": "192"
      },
      {
        "name": "Page",
        "args": [
          {
            "k": "page",
            "t": "str",
            "m": "len:32"
          },
          {
            "k": "title",
            "t": "str",
            "m": "len:14"
          },
          {
            "k": "icon",
            "t": "str",
            "m": "len:19"
          }
        ],
        "time": "282"
      },
      {
        "name": "Page",
        "args": [
          {
            "k": "page",
            "t": "str",
            "m": "len:26"
          },
          {
            "k": "title",
            "t": "str",
            "m": "len:23"
          },
          {
            "k": "icon",
            "t": "str",
            "m": "len:18"
          }
        ],
        "time": "665"
      },
      {
        "name": "Page",
        "args": [
          {
            "k": "page",
            "t": "str",
            "m": "len:30"
          },
          {
            "k": "title",
            "t": "str",
            "m": "len:12"
          },
          {
            "k": "icon",
            "t": "str",
            "m": "len:17"
          }
        ],
        "time": "439"
      },
      {
        "name": "Page",
        "args": [
          {
            "k": "page",
            "t": "str",
            "m": "len:7"
          },
          {
            "k": "title",
            "t": "str",
            "m": "len:4"
          },
          {
            "k": "icon",
            "t": "str",
            "m": "len:15"
          },
          {
            "k": "default",
            "t": "bool",
            "m": "val:True"
          }
        ],
        "time": "205"
      },
      {
        "name": "Page",
        "args": [
          {
            "k": "page",
            "t": "str",
            "m": "len:22"
          },
          {
            "k": "title",
            "t": "str",
            "m": "len:8"
          },
          {
            "k": "icon",
            "t": "str",
            "m": "len:22"
          }
        ],
        "time": "153"
      },
      {
        "name": "Page",
        "args": [
          {
            "k": "page",
            "t": "str",
            "m": "len:19"
          },
          {
            "k": "title",
            "t": "str",
            "m": "len:12"
          },
          {
            "k": "icon",
            "t": "str",
            "m": "len:15"
          }
        ],
        "time": "136"
      },
      {
        "name": "Page",
        "args": [
          {
            "k": "page",
            "t": "str",
            "m": "len:26"
          },
          {
            "k": "title",
            "t": "str",
            "m": "len:12"
          },
          {
            "k": "icon",
            "t": "str",
            "m": "len:31"
          }
        ],
        "time": "141"
      },
      {
        "name": "Page",
        "args": [
          {
            "k": "page",
            "t": "str",
            "m": "len:35"
          },
          {
            "k": "title",
            "t": "str",
            "m": "len:17"
          },
          {
            "k": "icon",
            "t": "str",
            "m": "len:18"
          },
          {
            "k": "url_path",
            "t": "str",
            "m": "len:17"
          }
        ],
        "time": "127"
      },
      {
        "name": "Page",
        "args": [
          {
            "k": "page",
            "t": "str",
            "m": "len:20"
          },
          {
            "k": "title",
            "t": "str",
            "m": "len:16"
          },
          {
            "k": "icon",
            "t": "str",
            "m": "len:18"
          }
        ],
        "time": "116"
      },
      {
        "name": "Page",
        "args": [
          {
            "k": "page",
            "t": "str",
            "m": "len:26"
          },
          {
            "k": "title",
            "t": "str",
            "m": "len:12"
          },
          {
            "k": "icon",
            "t": "str",
            "m": "len:21"
          }
        ],
        "time": "116"
      },
      {
        "name": "Page",
        "args": [
          {
            "k": "page",
            "t": "str",
            "m": "len:29"
          },
          {
            "k": "title",
            "t": "str",
            "m": "len:15"
          },
          {
            "k": "icon",
            "t": "str",
            "m": "len:23"
          }
        ],
        "time": "117"
      },
      {
        "name": "Page",
        "args": [
          {
            "k": "page",
            "t": "str",
            "m": "len:36"
          },
          {
            "k": "title",
            "t": "str",
            "m": "len:20"
          },
          {
            "k": "icon",
            "t": "str",
            "m": "len:16"
          }
        ],
        "time": "118"
      },
      {
        "name": "Page",
        "args": [
          {
            "k": "page",
            "t": "str",
            "m": "len:20"
          },
          {
            "k": "title",
            "t": "str",
            "m": "len:19"
          },
          {
            "k": "icon",
            "t": "str",
            "m": "len:20"
          }
        ],
        "time": "115"
      },
      {
        "name": "Page",
        "args": [
          {
            "k": "page",
            "t": "str",
            "m": "len:31"
          },
          {
            "k": "title",
            "t": "str",
            "m": "len:12"
          },
          {
            "k": "icon",
            "t": "str",
            "m": "len:14"
          }
        ],
        "time": "121"
      },
      {
        "name": "Page",
        "args": [
          {
            "k": "page",
            "t": "str",
            "m": "len:29"
          },
          {
            "k": "title",
            "t": "str",
            "m": "len:21"
          },
          {
            "k": "icon",
            "t": "str",
            "m": "len:18"
          }
        ],
        "time": "115"
      },
      {
        "name": "Page",
        "args": [
          {
            "k": "page",
            "t": "str",
            "m": "len:22"
          },
          {
            "k": "title",
            "t": "str",
            "m": "len:17"
          },
          {
            "k": "icon",
            "t": "str",
            "m": "len:18"
          }
        ],
        "time": "156"
      },
      {
        "name": "Page",
        "args": [
          {
            "k": "page",
            "t": "str",
            "m": "len:28"
          },
          {
            "k": "title",
            "t": "str",
            "m": "len:14"
          },
          {
            "k": "icon",
            "t": "str",
            "m": "len:31"
          }
        ],
        "time": "130"
      },
      {
        "name": "Page",
        "args": [
          {
            "k": "page",
            "t": "str",
            "m": "len:24"
          },
          {
            "k": "title",
            "t": "str",
            "m": "len:10"
          },
          {
            "k": "icon",
            "t": "str",
            "m": "len:14"
          }
        ],
        "time": "116"
      },
      {
        "name": "Page",
        "args": [
          {
            "k": "page",
            "t": "str",
            "m": "len:29"
          },
          {
            "k": "title",
            "t": "str",
            "m": "len:8"
          },
          {
            "k": "url_path",
            "t": "str",
            "m": "len:15"
          },
          {
            "k": "icon",
            "t": "str",
            "m": "len:22"
          }
        ],
        "time": "120"
      },
      {
        "name": "Page",
        "args": [
          {
            "k": "page",
            "t": "str",
            "m": "len:35"
          },
          {
            "k": "title",
            "t": "str",
            "m": "len:14"
          },
          {
            "k": "url_path",
            "t": "str",
            "m": "len:21"
          },
          {
            "k": "icon",
            "t": "str",
            "m": "len:19"
          }
        ],
        "time": "171"
      },
      {
        "name": "Page",
        "args": [
          {
            "k": "page",
            "t": "str",
            "m": "len:33"
          },
          {
            "k": "title",
            "t": "str",
            "m": "len:12"
          },
          {
            "k": "url_path",
            "t": "str",
            "m": "len:19"
          },
          {
            "k": "icon",
            "t": "str",
            "m": "len:17"
          }
        ],
        "time": "141"
      },
      {
        "name": "Page",
        "args": [
          {
            "k": "page",
            "t": "str",
            "m": "len:32"
          },
          {
            "k": "title",
            "t": "str",
            "m": "len:11"
          },
          {
            "k": "url_path",
            "t": "str",
            "m": "len:18"
          },
          {
            "k": "icon",
            "t": "str",
            "m": "len:23"
          }
        ],
        "time": "186"
      },
      {
        "name": "navigation",
        "args": [
          {
            "k": "pages",
            "t": "dict",
            "m": "len:10"
          },
          {
            "k": "position",
            "t": "str",
            "m": "len:3"
          }
        ],
        "time": "505"
      },
      {
        "name": "set_page_config",
        "args": [
          {
            "k": "page_title",
            "t": "str",
            "m": "len:24"
          },
          {
            "k": "layout",
            "t": "str",
            "m": "len:4"
          },
          {
            "k": "page_icon",
            "t": "str",
            "m": "len:11"
          }
        ],
        "time": "1734"
      },
      {
        "name": "logo",
        "args": [
          {
            "k": "image",
            "t": "str",
            "m": "len:11"
          }
        ],
        "time": "1362"
      },
      {
        "name": "markdown",
        "args": [
          {
            "k": "body",
            "t": "str",
            "m": "len:94",
            "p": 1
          },
          {
            "k": "unsafe_allow_html",
            "t": "bool",
            "m": "val:True"
          }
        ],
        "time": "220"
      },
      {
        "name": "title",
        "args": [
          {
            "k": "body",
            "t": "str",
            "m": "len:24",
            "p": 1
          }
        ],
        "time": "174"
      },
      {
        "name": "context.headers",
        "time": "71"
      },
      {
        "name": "query_params.get_item",
        "args": [
          {
            "k": "key",
            "t": "str",
            "m": "len:6",
            "p": 1
          }
        ]
      },
      {
        "name": "columns",
        "args": [
          {
            "k": "spec",
            "t": "int",
            "p": 1
          }
        ],
        "time": "525"
      },
      {
        "name": "session_state.set_item",
        "args": [
          {
            "k": "key",
            "t": "str",
            "m": "len:12",
            "p": 1
          },
          {
            "k": "value",
            "t": "dict",
            "m": "len:0",
            "p": 2
          }
        ],
        "time": "80"
      },
      {
        "name": "session_state.set_item",
        "args": [
          {
            "k": "key",
            "t": "str",
            "m": "len:14",
            "p": 1
          },
          {
            "k": "value",
            "t": "dict",
            "m": "len:0",
            "p": 2
          }
        ],
        "time": "51"
      },
      {
        "name": "session_state.set_item",
        "args": [
          {
            "k": "key",
            "t": "str",
            "m": "len:16",
            "p": 1
          },
          {
            "k": "value",
            "t": "list",
            "m": "len:0",
            "p": 2
          }
        ],
        "time": "48"
      },
      {
        "name": "query_params.get_all",
        "args": [
          {
            "k": "key",
            "t": "str",
            "m": "len:12",
            "p": 1
          }
        ],
        "time": "56"
      },
      {
        "name": "text_input",
        "args": [
          {
            "k": "label",
            "t": "str",
            "m": "len:52"
          },
          {
            "k": "max_chars",
            "t": "int"
          },
          {
            "k": "key",
            "t": "str",
            "m": "len:12"
          },
          {
            "k": "on_change",
            "t": "function"
          },
          {
            "k": "value",
            "t": "str",
            "m": "len:42"
          }
        ],
        "time": "397"
      },
      {
        "name": "_cache_data_object",
        "args": [
          {
            "k": "key",
            "t": "str",
            "m": "len:32",
            "p": 1
          },
          {
            "k": "value",
            "t": "dict",
            "m": "len:4",
            "p": 2
          },
          {
            "k": "messages",
            "t": "list",
            "m": "len:0",
            "p": 3
          }
        ],
        "time": "256"
      },
      {
        "name": "query_params.set_attr",
        "args": [
          {
            "k": "key",
            "t": "str",
            "m": "len:12",
            "p": 1
          },
          {
            "k": "value",
            "t": "str",
            "m": "len:42",
            "p": 2
          }
        ],
        "time": "218"
      },
      {
        "name": "_cache_data_object",
        "args": [
          {
            "k": "key",
            "t": "str",
            "m": "len:32",
            "p": 1
          },
          {
            "k": "value",
            "t": "dict",
            "m": "len:9",
            "p": 2
          },
          {
            "k": "messages",
            "t": "list",
            "m": "len:0",
            "p": 3
          }
        ],
        "time": "302"
      },
      {
        "name": "image",
        "args": [
          {
            "k": "image",
            "t": "str",
            "m": "len:71",
            "p": 1
          },
          {
            "k": "width",
            "t": "int"
          }
        ],
        "time": "457"
      },
      {
        "name": "caption",
        "args": [
          {
            "k": "body",
            "t": "str",
            "m": "len:6",
            "p": 1
          }
        ],
        "time": "212"
      },
      {
        "name": "divider",
        "time": "433"
      },
      {
        "name": "columns",
        "args": [
          {
            "k": "spec",
            "t": "int",
            "p": 1
          }
        ],
        "time": "1323"
      },
      {
        "name": "badge",
        "args": [
          {
            "k": "label",
            "t": "str",
            "m": "len:10",
            "p": 1
          },
          {
            "k": "icon",
            "t": "str",
            "m": "len:24"
          },
          {
            "k": "color",
            "t": "str",
            "m": "len:4"
          }
        ],
        "time": "291"
      },
      {
        "name": "caption",
        "args": [
          {
            "k": "body",
            "t": "str",
            "m": "len:30",
            "p": 1
          }
        ],
        "time": "197"
      },
      {
        "name": "badge",
        "args": [
          {
            "k": "label",
            "t": "str",
            "m": "len:18",
            "p": 1
          },
          {
            "k": "icon",
            "t": "str",
            "m": "len:17"
          },
          {
            "k": "color",
            "t": "str",
            "m": "len:5"
          }
        ],
        "time": "191"
      },
      {
        "name": "caption",
        "args": [
          {
            "k": "body",
            "t": "str",
            "m": "len:37",
            "p": 1
          }
        ],
        "time": "162"
      },
      {
        "name": "badge",
        "args": [
          {
            "k": "label",
            "t": "str",
            "m": "len:10",
            "p": 1
          },
          {
            "k": "icon",
            "t": "str",
            "m": "len:23"
          },
          {
            "k": "color",
            "t": "str",
            "m": "len:4"
          }
        ],
        "time": "169"
      },
      {
        "name": "caption",
        "args": [
          {
            "k": "body",
            "t": "str",
            "m": "len:20",
            "p": 1
          }
        ],
        "time": "154"
      },
      {
        "name": "divider",
        "time": "171"
      },
      {
        "name": "button",
        "args": [
          {
            "k": "label",
            "t": "str",
            "m": "len:40",
            "p": 1
          }
        ],
        "time": "389"
      },
      {
        "name": "_cache_data_object",
        "args": [
          {
            "k": "key",
            "t": "str",
            "m": "len:32",
            "p": 1
          },
          {
            "k": "value",
            "t": "dict",
            "m": "len:0",
            "p": 2
          },
          {
            "k": "messages",
            "t": "list",
            "m": "len:0",
            "p": 3
          }
        ],
        "time": "275"
      },
      {
        "name": "columns",
        "args": [
          {
            "k": "spec",
            "t": "int",
            "p": 1
          }
        ],
        "time": "731"
      },
      {
        "name": "markdown",
        "args": [
          {
            "k": "body",
            "t": "str",
            "m": "len:472",
            "p": 1
          },
          {
            "k": "unsafe_allow_html",
            "t": "bool",
            "m": "val:True"
          }
        ],
        "time": "242"
      },
      {
        "name": "empty",
        "time": "424"
      },
      {
        "name": "_cache_data_object",
        "args": [
          {
            "k": "key",
            "t": "str",
            "m": "len:32",
            "p": 1
          },
          {
            "k": "value",
            "t": "float",
            "p": 2
          },
          {
            "k": "messages",
            "t": "list",
            "m": "len:0",
            "p": 3
          }
        ],
        "time": "302"
      },
      {
        "name": "empty",
        "time": "729"
      },
      {
        "name": "markdown",
        "args": [
          {
            "k": "body",
            "t": "str",
            "m": "len:1051",
            "p": 1
          },
          {
            "k": "unsafe_allow_html",
            "t": "bool",
            "m": "val:True"
          }
        ],
        "time": "487"
      },
      {
        "name": "markdown",
        "args": [
          {
            "k": "body",
            "t": "str",
            "m": "len:519",
            "p": 1
          },
          {
            "k": "unsafe_allow_html",
            "t": "bool",
            "m": "val:True"
          }
        ],
        "time": "376"
      },
      {
        "name": "cache_data",
        "args": [
          {
            "k": "func",
            "t": "NoneType"
          },
          {
            "k": "ttl",
            "t": "str",
            "m": "len:2"
          },
          {
            "k": "max_entries",
            "t": "int"
          },
          {
            "k": "persist",
            "t": "NoneType"
          },
          {
            "k": "show_spinner",
            "t": "bool",
            "m": "val:False"
          },
          {
            "k": "show_time",
            "t": "bool",
            "m": "val:False"
          },
          {
            "k": "hash_funcs",
            "t": "NoneType"
          }
        ],
        "time": "151"
      },
      {
        "name": "caption",
        "args": [
          {
            "k": "body",
            "t": "str",
            "m": "len:11",
            "p": 1
          }
        ],
        "time": "323"
      },
      {
        "name": "columns",
        "args": [
          {
            "k": "spec",
            "t": "int",
            "p": 1
          }
        ],
        "time": "791"
      },
      {
        "name": "_cache_data_object",
        "args": [
          {
            "k": "key",
            "t": "str",
            "m": "len:32",
            "p": 1
          },
          {
            "k": "value",
            "t": "requests.models.Response",
            "p": 2
          },
          {
            "k": "messages",
            "t": "list",
            "m": "len:0",
            "p": 3
          }
        ],
        "time": "423"
      },
      {
        "name": "_cache_data_object",
        "args": [
          {
            "k": "key",
            "t": "str",
            "m": "len:32",
            "p": 1
          },
          {
            "k": "value",
            "t": "requests.models.Response",
            "p": 2
          },
          {
            "k": "messages",
            "t": "list",
            "m": "len:0",
            "p": 3
          }
        ],
        "time": "440"
      },
      {
        "name": "_cache_data_object",
        "args": [
          {
            "k": "key",
            "t": "str",
            "m": "len:32",
            "p": 1
          },
          {
            "k": "value",
            "t": "requests.models.Response",
            "p": 2
          },
          {
            "k": "messages",
            "t": "list",
            "m": "len:0",
            "p": 3
          }
        ],
        "time": "462"
      },
      {
        "name": "_cache_data_object",
        "args": [
          {
            "k": "key",
            "t": "str",
            "m": "len:32",
            "p": 1
          },
          {
            "k": "value",
            "t": "requests.models.Response",
            "p": 2
          },
          {
            "k": "messages",
            "t": "list",
            "m": "len:0",
            "p": 3
          }
        ],
        "time": "338"
      },
      {
        "name": "markdown",
        "args": [
          {
            "k": "body",
            "t": "str",
            "m": "len:423",
            "p": 1
          },
          {
            "k": "unsafe_allow_html",
            "t": "bool",
            "m": "val:True"
          }
        ],
        "time": "458"
      },
      {
        "name": "caption",
        "args": [
          {
            "k": "body",
            "t": "str",
            "m": "len:178",
            "p": 1
          }
        ],
        "time": "240"
      },
      {
        "name": "divider",
        "time": "156"
      },
      {
        "name": "cache_data",
        "args": [
          {
            "k": "func",
            "t": "NoneType"
          },
          {
            "k": "ttl",
            "t": "str",
            "m": "len:2"
          },
          {
            "k": "max_entries",
            "t": "int"
          },
          {
            "k": "persist",
            "t": "NoneType"
          },
          {
            "k": "show_spinner",
            "t": "bool",
            "m": "val:False"
          },
          {
            "k": "show_time",
            "t": "bool",
            "m": "val:False"
          },
          {
            "k": "hash_funcs",
            "t": "NoneType"
          }
        ],
        "time": "249"
      },
      {
        "name": "empty",
        "time": "718"
      },
      {
        "name": "empty",
        "time": "327"
      },
      {
        "name": "empty",
        "time": "144"
      },
      {
        "name": "empty",
        "time": "140"
      },
      {
        "name": "_cache_data_object",
        "args": [
          {
            "k": "key",
            "t": "str",
            "m": "len:32",
            "p": 1
          },
          {
            "k": "value",
            "t": "DataFrame",
            "m": "len:15",
            "p": 2
          },
          {
            "k": "messages",
            "t": "list",
            "m": "len:0",
            "p": 3
          }
        ],
        "time": "406"
      },
      {
        "name": "empty",
        "time": "292"
      },
      {
        "name": "_cache_data_object",
        "args": [
          {
            "k": "key",
            "t": "str",
            "m": "len:32",
            "p": 1
          },
          {
            "k": "value",
            "t": "float",
            "p": 2
          },
          {
            "k": "messages",
            "t": "list",
            "m": "len:0",
            "p": 3
          }
        ],
        "time": "206"
      },
      {
        "name": "cache_data",
        "args": [
          {
            "k": "func",
            "t": "NoneType"
          },
          {
            "k": "ttl",
            "t": "int"
          },
          {
            "k": "max_entries",
            "t": "int"
          },
          {
            "k": "persist",
            "t": "NoneType"
          },
          {
            "k": "show_spinner",
            "t": "bool",
            "m": "val:False"
          },
          {
            "k": "show_time",
            "t": "bool",
            "m": "val:False"
          },
          {
            "k": "hash_funcs",
            "t": "NoneType"
          }
        ],
        "time": "111"
      },
      {
        "name": "_cache_data_object",
        "args": [
          {
            "k": "key",
            "t": "str",
            "m": "len:32",
            "p": 1
          },
          {
            "k": "value",
            "t": "str",
            "m": "len:961",
            "p": 2
          },
          {
            "k": "messages",
            "t": "list",
            "m": "len:0",
            "p": 3
          }
        ],
        "time": "296"
      },
      {
        "name": "markdown",
        "args": [
          {
            "k": "body",
            "t": "str",
            "m": "len:961",
            "p": 1
          },
          {
            "k": "unsafe_allow_html",
            "t": "bool",
            "m": "val:True"
          }
        ],
        "time": "648"
      },
      {
        "name": "cache_data",
        "args": [
          {
            "k": "func",
            "t": "NoneType"
          },
          {
            "k": "ttl",
            "t": "int"
          },
          {
            "k": "max_entries",
            "t": "int"
          },
          {
            "k": "persist",
            "t": "NoneType"
          },
          {
            "k": "show_spinner",
            "t": "bool",
            "m": "val:True"
          },
          {
            "k": "show_time",
            "t": "bool",
            "m": "val:False"
          },
          {
            "k": "hash_funcs",
            "t": "NoneType"
          }
        ],
        "time": "218"
      },
      {
        "name": "empty",
        "time": "367"
      },
      {
        "name": "_cache_data_object",
        "args": [
          {
            "k": "key",
            "t": "str",
            "m": "len:32",
            "p": 1
          },
          {
            "k": "value",
            "t": "DataFrame",
            "m": "len:1",
            "p": 2
          },
          {
            "k": "messages",
            "t": "list",
            "m": "len:0",
            "p": 3
          }
        ],
        "time": "402"
      },
      {
        "name": "empty",
        "time": "320"
      },
      {
        "name": "empty",
        "time": "280"
      },
      {
        "name": "_cache_data_object",
        "args": [
          {
            "k": "key",
            "t": "str",
            "m": "len:32",
            "p": 1
          },
          {
            "k": "value",
            "t": "tuple",
            "m": "len:2",
            "p": 2
          },
          {
            "k": "messages",
            "t": "list",
            "m": "len:0",
            "p": 3
          }
        ],
        "time": "24299"
      },
      {
        "name": "empty",
        "time": "668"
      },
      {
        "name": "plotly_chart",
        "args": [
          {
            "k": "figure_or_data",
            "t": "PlotlyFigure",
            "p": 1
          }
        ],
        "time": "40431"
      },
      {
        "name": "markdown",
        "args": [
          {
            "k": "body",
            "t": "str",
            "m": "len:1846",
            "p": 1
          },
          {
            "k": "unsafe_allow_html",
            "t": "bool",
            "m": "val:True"
          }
        ],
        "time": "513"
      },
      {
        "name": "cache_data",
        "args": [
          {
            "k": "func",
            "t": "NoneType"
          },
          {
            "k": "ttl",
            "t": "int"
          },
          {
            "k": "max_entries",
            "t": "int"
          },
          {
            "k": "persist",
            "t": "NoneType"
          },
          {
            "k": "show_spinner",
            "t": "bool",
            "m": "val:False"
          },
          {
            "k": "show_time",
            "t": "bool",
            "m": "val:False"
          },
          {
            "k": "hash_funcs",
            "t": "NoneType"
          }
        ],
        "time": "182"
      },
      {
        "name": "markdown",
        "args": [
          {
            "k": "body",
            "t": "str",
            "m": "len:0",
            "p": 1
          }
        ],
        "time": "1003"
      },
      {
        "name": "metric",
        "args": [
          {
            "k": "label",
            "t": "str",
            "m": "len:35"
          },
          {
            "k": "value",
            "t": "str",
            "m": "len:2"
          },
          {
            "k": "chart_data",
            "t": "list",
            "m": "len:30"
          },
          {
            "k": "chart_type",
            "t": "str",
            "m": "len:4"
          }
        ],
        "time": "419"
      },
      {
        "name": "markdown",
        "args": [
          {
            "k": "body",
            "t": "str",
            "m": "len:0",
            "p": 1
          }
        ],
        "time": "237"
      },
      {
        "name": "_cache_data_object",
        "args": [
          {
            "k": "key",
            "t": "str",
            "m": "len:32",
            "p": 1
          },
          {
            "k": "value",
            "t": "NoneType",
            "p": 2
          },
          {
            "k": "messages",
            "t": "list",
            "m": "len:3",
            "p": 3
          }
        ],
        "time": "198"
      },
      {
        "name": "columns",
        "args": [
          {
            "k": "spec",
            "t": "int",
            "p": 1
          }
        ],
        "time": "1209"
      },
      {
        "name": "markdown",
        "args": [
          {
            "k": "body",
            "t": "str",
            "m": "len:506",
            "p": 1
          },
          {
            "k": "unsafe_allow_html",
            "t": "bool",
            "m": "val:True"
          }
        ],
        "time": "305"
      },
      {
        "name": "column_config.NumberColumn",
        "args": [
          {
            "k": "label",
            "t": "str",
            "m": "len:12"
          },
          {
            "k": "format",
            "t": "str",
            "m": "len:6"
          },
          {
            "k": "help",
            "t": "str",
            "m": "len:81"
          }
        ],
        "time": "154"
      },
      {
        "name": "column_config.NumberColumn",
        "args": [
          {
            "k": "label",
            "t": "str",
            "m": "len:14"
          },
          {
            "k": "format",
            "t": "str",
            "m": "len:6"
          },
          {
            "k": "help",
            "t": "str",
            "m": "len:75"
          }
        ],
        "time": "80"
      },
      {
        "name": "column_config.NumberColumn",
        "args": [
          {
            "k": "label",
            "t": "str",
            "m": "len:11"
          },
          {
            "k": "format",
            "t": "str",
            "m": "len:6"
          },
          {
            "k": "help",
            "t": "str",
            "m": "len:73"
          }
        ],
        "time": "67"
      },
      {
        "name": "column_config.NumberColumn",
        "args": [
          {
            "k": "label",
            "t": "str",
            "m": "len:13"
          },
          {
            "k": "format",
            "t": "str",
            "m": "len:6"
          },
          {
            "k": "help",
            "t": "str",
            "m": "len:55"
          }
        ],
        "time": "63"
      },
      {
        "name": "column_config.NumberColumn",
        "args": [
          {
            "k": "label",
            "t": "str",
            "m": "len:13"
          },
          {
            "k": "format",
            "t": "str",
            "m": "len:6"
          },
          {
            "k": "help",
            "t": "str",
            "m": "len:31"
          }
        ],
        "time": "62"
      },
      {
        "name": "column_config.NumberColumn",
        "args": [
          {
            "k": "label",
            "t": "str",
            "m": "len:15"
          },
          {
            "k": "help",
            "t": "str",
            "m": "len:47"
          }
        ],
        "time": "57"
      },
      {
        "name": "column_config.NumberColumn",
        "args": [
          {
            "k": "label",
            "t": "str",
            "m": "len:15"
          },
          {
            "k": "format",
            "t": "str",
            "m": "len:7"
          },
          {
            "k": "help",
            "t": "str",
            "m": "len:52"
          }
        ],
        "time": "61"
      },
      {
        "name": "column_config.NumberColumn",
        "args": [
          {
            "k": "label",
            "t": "str",
            "m": "len:14"
          },
          {
            "k": "format",
            "t": "str",
            "m": "len:6"
          },
          {
            "k": "help",
            "t": "str",
            "m": "len:44"
          }
        ],
        "time": "59"
      },
      {
        "name": "column_config.NumberColumn",
        "args": [
          {
            "k": "label",
            "t": "str",
            "m": "len:8"
          },
          {
            "k": "format",
            "t": "str",
            "m": "len:6"
          },
          {
            "k": "help",
            "t": "str",
            "m": "len:56"
          }
        ],
        "time": "60"
      },
      {
        "name": "data_editor",
        "args": [
          {
            "k": "data",
            "t": "PandasStyler",
            "p": 1
          },
          {
            "k": "use_container_width",
            "t": "bool",
            "m": "val:True"
          },
          {
            "k": "hide_index",
            "t": "bool",
            "m": "val:True"
          },
          {
            "k": "disabled",
            "t": "bool",
            "m": "val:True"
          },
          {
            "k": "key",
            "t": "str",
            "m": "len:6"
          },
          {
            "k": "column_config",
            "t": "dict",
            "m": "len:9"
          },
          {
            "k": "column_order",
            "t": "list",
            "m": "len:9"
          }
        ],
        "time": "11784"
      },
      {
        "name": "markdown",
        "args": [
          {
            "k": "body",
            "t": "str",
            "m": "len:510",
            "p": 1
          },
          {
            "k": "unsafe_allow_html",
            "t": "bool",
            "m": "val:True"
          }
        ],
        "time": "615"
      },
      {
        "name": "data_editor",
        "args": [
          {
            "k": "data",
            "t": "PandasStyler",
            "p": 1
          },
          {
            "k": "use_container_width",
            "t": "bool",
            "m": "val:True"
          },
          {
            "k": "hide_index",
            "t": "bool",
            "m": "val:True"
          },
          {
            "k": "disabled",
            "t": "bool",
            "m": "val:True"
          },
          {
            "k": "key",
            "t": "str",
            "m": "len:8"
          },
          {
            "k": "column_config",
            "t": "dict",
            "m": "len:9"
          },
          {
            "k": "column_order",
            "t": "list",
            "m": "len:8"
          }
        ],
        "time": "20201"
      },
      {
        "name": "markdown",
        "args": [
          {
            "k": "body",
            "t": "str",
            "m": "len:1084",
            "p": 1
          },
          {
            "k": "unsafe_allow_html",
            "t": "bool",
            "m": "val:True"
          }
        ],
        "time": "612"
      },
      {
        "name": "markdown",
        "args": [
          {
            "k": "body",
            "t": "str",
            "m": "len:1181",
            "p": 1
          },
          {
            "k": "unsafe_allow_html",
            "t": "bool",
            "m": "val:True"
          }
        ],
        "time": "324"
      },
      {
        "name": "markdown",
        "args": [
          {
            "k": "body",
            "t": "str",
            "m": "len:0",
            "p": 1
          }
        ],
        "time": "197"
      },
      {
        "name": "subheader",
        "args": [
          {
            "k": "body",
            "t": "str",
            "m": "len:24",
            "p": 1
          }
        ],
        "time": "198"
      },
      {
        "name": "caption",
        "args": [
          {
            "k": "body",
            "t": "str",
            "m": "len:133",
            "p": 1
          }
        ],
        "time": "174"
      },
      {
        "name": "plotly_chart",
        "args": [
          {
            "k": "figure_or_data",
            "t": "PlotlyFigure",
            "p": 1
          },
          {
            "k": "use_container_width",
            "t": "bool",
            "m": "val:True"
          }
        ],
        "time": "10320"
      },
      {
        "name": "plotly_chart",
        "args": [
          {
            "k": "figure_or_data",
            "t": "PlotlyFigure",
            "p": 1
          }
        ],
        "time": "1067"
      },
      {
        "name": "columns",
        "args": [
          {
            "k": "spec",
            "t": "int",
            "p": 1
          }
        ],
        "time": "664"
      },
      {
        "name": "subheader",
        "args": [
          {
            "k": "body",
            "t": "str",
            "m": "len:34",
            "p": 1
          }
        ],
        "time": "273"
      },
      {
        "name": "plotly_chart",
        "args": [
          {
            "k": "figure_or_data",
            "t": "PlotlyFigure",
            "p": 1
          },
          {
            "k": "use_container_width",
            "t": "bool",
            "m": "val:True"
          }
        ],
        "time": "1635"
      },
      {
        "name": "subheader",
        "args": [
          {
            "k": "body",
            "t": "str",
            "m": "len:32",
            "p": 1
          }
        ],
        "time": "290"
      },
      {
        "name": "plotly_chart",
        "args": [
          {
            "k": "figure_or_data",
            "t": "PlotlyFigure",
            "p": 1
          },
          {
            "k": "use_container_width",
            "t": "bool",
            "m": "val:True"
          }
        ],
        "time": "1384"
      },
      {
        "name": "cache_data",
        "args": [
          {
            "k": "func",
            "t": "NoneType"
          },
          {
            "k": "ttl",
            "t": "int"
          },
          {
            "k": "max_entries",
            "t": "int"
          },
          {
            "k": "persist",
            "t": "NoneType"
          },
          {
            "k": "show_spinner",
            "t": "str",
            "m": "len:21"
          },
          {
            "k": "show_time",
            "t": "bool",
            "m": "val:False"
          },
          {
            "k": "hash_funcs",
            "t": "NoneType"
          }
        ],
        "time": "127"
      },
      {
        "name": "cache_data",
        "args": [
          {
            "k": "func",
            "t": "NoneType"
          },
          {
            "k": "ttl",
            "t": "int"
          },
          {
            "k": "max_entries",
            "t": "int"
          },
          {
            "k": "persist",
            "t": "NoneType"
          },
          {
            "k": "show_spinner",
            "t": "str",
            "m": "len:29"
          },
          {
            "k": "show_time",
            "t": "bool",
            "m": "val:False"
          },
          {
            "k": "hash_funcs",
            "t": "NoneType"
          }
        ],
        "time": "137"
      },
      {
        "name": "empty",
        "time": "290"
      },
      {
        "name": "_cache_data_object",
        "args": [
          {
            "k": "key",
            "t": "str",
            "m": "len:32",
            "p": 1
          },
          {
            "k": "value",
            "t": "DataFrame",
            "m": "len:1",
            "p": 2
          },
          {
            "k": "messages",
            "t": "list",
            "m": "len:0",
            "p": 3
          }
        ],
        "time": "470"
      },
      {
        "name": "empty",
        "time": "630"
      },
      {
        "name": "empty",
        "time": "250"
      },
      {
        "name": "_cache_data_object",
        "args": [
          {
            "k": "key",
            "t": "str",
            "m": "len:32",
            "p": 1
          },
          {
            "k": "value",
            "t": "DataFrame",
            "m": "len:1",
            "p": 2
          },
          {
            "k": "messages",
            "t": "list",
            "m": "len:0",
            "p": 3
          }
        ],
        "time": "280"
      },
      {
        "name": "empty",
        "time": "269"
      },
      {
        "name": "columns",
        "args": [
          {
            "k": "spec",
            "t": "int",
            "p": 1
          }
        ],
        "time": "758"
      },
      {
        "name": "subheader",
        "args": [
          {
            "k": "body",
            "t": "str",
            "m": "len:22",
            "p": 1
          }
        ],
        "time": "259"
      },
      {
        "name": "plotly_chart",
        "args": [
          {
            "k": "figure_or_data",
            "t": "PlotlyFigure",
            "p": 1
          },
          {
            "k": "use_container_width",
            "t": "bool",
            "m": "val:True"
          }
        ],
        "time": "1802"
      },
      {
        "name": "subheader",
        "args": [
          {
            "k": "body",
            "t": "str",
            "m": "len:23",
            "p": 1
          }
        ],
        "time": "471"
      },
      {
        "name": "markdown",
        "args": [
          {
            "k": "body",
            "t": "str",
            "m": "len:595",
            "p": 1
          },
          {
            "k": "unsafe_allow_html",
            "t": "bool",
            "m": "val:True"
          }
        ],
        "time": "487"
      },
      {
        "name": "plotly_chart",
        "args": [
          {
            "k": "figure_or_data",
            "t": "PlotlyFigure",
            "p": 1
          },
          {
            "k": "use_container_width",
            "t": "bool",
            "m": "val:True"
          }
        ],
        "time": "1368"
      },
      {
        "name": "subheader",
        "args": [
          {
            "k": "body",
            "t": "str",
            "m": "len:20",
            "p": 1
          }
        ],
        "time": "592"
      },
      {
        "name": "plotly_chart",
        "args": [
          {
            "k": "figure_or_data",
            "t": "PlotlyFigure",
            "p": 1
          },
          {
            "k": "use_container_width",
            "t": "bool",
            "m": "val:True"
          }
        ],
        "time": "3191"
      },
      {
        "name": "subheader",
        "args": [
          {
            "k": "body",
            "t": "str",
            "m": "len:57",
            "p": 1
          }
        ],
        "time": "419"
      },
      {
        "name": "query_params.get_item",
        "args": [
          {
            "k": "key",
            "t": "str",
            "m": "len:6",
            "p": 1
          }
        ]
      },
      {
        "name": "query_params.set_item",
        "args": [
          {
            "k": "key",
            "t": "str",
            "m": "len:6",
            "p": 1
          },
          {
            "k": "value",
            "t": "str",
            "m": "len:58",
            "p": 2
          }
        ],
        "time": "262"
      },
      {
        "name": "query_params.get_all",
        "args": [
          {
            "k": "key",
            "t": "str",
            "m": "len:6",
            "p": 1
          }
        ],
        "time": "112"
      },
      {
        "name": "selectbox",
        "args": [
          {
            "k": "label",
            "t": "str",
            "m": "len:38"
          },
          {
            "k": "options",
            "t": "list",
            "m": "len:15"
          },
          {
            "k": "key",
            "t": "str",
            "m": "len:6"
          },
          {
            "k": "on_change",
            "t": "function"
          },
          {
            "k": "index",
            "t": "int"
          }
        ],
        "time": "859"
      },
      {
        "name": "empty",
        "time": "247"
      },
      {
        "name": "_cache_data_object",
        "args": [
          {
            "k": "key",
            "t": "str",
            "m": "len:32",
            "p": 1
          },
          {
            "k": "value",
            "t": "list",
            "m": "len:1",
            "p": 2
          },
          {
            "k": "messages",
            "t": "list",
            "m": "len:3",
            "p": 3
          }
        ],
        "time": "310"
      },
      {
        "name": "empty",
        "time": "10756"
      },
      {
        "name": "_cache_data_object",
        "args": [
          {
            "k": "key",
            "t": "str",
            "m": "len:32",
            "p": 1
          },
          {
            "k": "value",
            "t": "dict",
            "m": "len:1",
            "p": 2
          },
          {
            "k": "messages",
            "t": "list",
            "m": "len:0",
            "p": 3
          }
        ],
        "time": "323"
      },
      {
        "name": "empty",
        "time": "5475"
      },
      {
        "name": "empty",
        "time": "173"
      },
      {
        "name": "_cache_data_object",
        "args": [
          {
            "k": "key",
            "t": "str",
            "m": "len:32",
            "p": 1
          },
          {
            "k": "value",
            "t": "list",
            "m": "len:4",
            "p": 2
          },
          {
            "k": "messages",
            "t": "list",
            "m": "len:3",
            "p": 3
          }
        ],
        "time": "224"
      },
      {
        "name": "_cache_data_object",
        "args": [
          {
            "k": "key",
            "t": "str",
            "m": "len:32",
            "p": 1
          },
          {
            "k": "value",
            "t": "dict",
            "m": "len:4",
            "p": 2
          },
          {
            "k": "messages",
            "t": "list",
            "m": "len:0",
            "p": 3
          }
        ],
        "time": "201"
      },
      {
        "name": "warning",
        "args": [
          {
            "k": "body",
            "t": "str",
            "m": "len:76",
            "p": 1
          }
        ],
        "time": "440"
      },
      {
        "name": "plotly_chart",
        "args": [
          {
            "k": "figure_or_data",
            "t": "PlotlyFigure",
            "p": 1
          }
        ],
        "time": "2282"
      },
      {
        "name": "plotly_chart",
        "args": [
          {
            "k": "figure_or_data",
            "t": "PlotlyFigure",
            "p": 1
          },
          {
            "k": "use_container_width",
            "t": "bool",
            "m": "val:True"
          }
        ],
        "time": "3841"
      },
      {
        "name": "cache_data",
        "args": [
          {
            "k": "func",
            "t": "NoneType"
          },
          {
            "k": "ttl",
            "t": "int"
          },
          {
            "k": "max_entries",
            "t": "int"
          },
          {
            "k": "persist",
            "t": "NoneType"
          },
          {
            "k": "show_spinner",
            "t": "str",
            "m": "len:21"
          },
          {
            "k": "show_time",
            "t": "bool",
            "m": "val:False"
          },
          {
            "k": "hash_funcs",
            "t": "NoneType"
          }
        ],
        "time": "214"
      },
      {
        "name": "empty",
        "time": "283"
      },
      {
        "name": "_cache_data_object",
        "args": [
          {
            "k": "key",
            "t": "str",
            "m": "len:32",
            "p": 1
          },
          {
            "k": "value",
            "t": "DataFrame",
            "m": "len:21",
            "p": 2
          },
          {
            "k": "messages",
            "t": "list",
            "m": "len:0",
            "p": 3
          }
        ],
        "time": "420"
      },
      {
        "name": "empty",
        "time": "303"
      },
      {
        "name": "subheader",
        "args": [
          {
            "k": "body",
            "t": "str",
            "m": "len:13",
            "p": 1
          }
        ],
        "time": "329"
      },
      {
        "name": "column_config.DatetimeColumn",
        "args": [
          {
            "k": "label",
            "t": "str",
            "m": "len:9"
          },
          {
            "k": "format",
            "t": "str",
            "m": "len:16"
          }
        ],
        "time": "121"
      },
      {
        "name": "column_config.TextColumn",
        "args": [
          {
            "k": "label",
            "t": "str",
            "m": "len:8"
          },
          {
            "k": "required",
            "t": "bool",
            "m": "val:False"
          },
          {
            "k": "help",
            "t": "str",
            "m": "len:29"
          }
        ],
        "time": "110"
      },
      {
        "name": "column_config.TextColumn",
        "args": [
          {
            "k": "label",
            "t": "str",
            "m": "len:4"
          },
          {
            "k": "help",
            "t": "str",
            "m": "len:29"
          }
        ],
        "time": "68"
      },
      {
        "name": "column_config.NumberColumn",
        "args": [
          {
            "k": "label",
            "t": "str",
            "m": "len:5"
          },
          {
            "k": "format",
            "t": "str",
            "m": "len:6"
          }
        ],
        "time": "64"
      },
      {
        "name": "column_config.NumberColumn",
        "args": [
          {
            "k": "label",
            "t": "str",
            "m": "len:10"
          },
          {
            "k": "format",
            "t": "str",
            "m": "len:6"
          }
        ],
        "time": "59"
      },
      {
        "name": "column_config.NumberColumn",
        "args": [
          {
            "k": "label",
            "t": "str",
            "m": "len:6"
          },
          {
            "k": "format",
            "t": "str",
            "m": "len:4"
          }
        ],
        "time": "57"
      },
      {
        "name": "column_config.TextColumn",
        "args": [
          {
            "k": "label",
            "t": "str",
            "m": "len:7"
          },
          {
            "k": "help",
            "t": "str",
            "m": "len:49"
          }
        ],
        "time": "52"
      },
      {
        "name": "data_editor",
        "args": [
          {
            "k": "data",
            "t": "PandasStyler",
            "p": 1
          },
          {
            "k": "hide_index",
            "t": "bool",
            "m": "val:True"
          },
          {
            "k": "use_container_width",
            "t": "bool",
            "m": "val:True"
          },
          {
            "k": "column_config",
            "t": "dict",
            "m": "len:7"
          },
          {
            "k": "column_order",
            "t": "list",
            "m": "len:7"
          },
          {
            "k": "disabled",
            "t": "bool",
            "m": "val:True"
          }
        ],
        "time": "11578"
      },
      {
        "name": "cache_data",
        "args": [
          {
            "k": "func",
            "t": "NoneType"
          },
          {
            "k": "ttl",
            "t": "int"
          },
          {
            "k": "max_entries",
            "t": "int"
          },
          {
            "k": "persist",
            "t": "NoneType"
          },
          {
            "k": "show_spinner",
            "t": "str",
            "m": "len:24"
          },
          {
            "k": "show_time",
            "t": "bool",
            "m": "val:False"
          },
          {
            "k": "hash_funcs",
            "t": "NoneType"
          }
        ],
        "time": "143"
      },
      {
        "name": "empty",
        "time": "218"
      },
      {
        "name": "_cache_data_object",
        "args": [
          {
            "k": "key",
            "t": "str",
            "m": "len:32",
            "p": 1
          },
          {
            "k": "value",
            "t": "DataFrame",
            "m": "len:6",
            "p": 2
          },
          {
            "k": "messages",
            "t": "list",
            "m": "len:0",
            "p": 3
          }
        ],
        "time": "253"
      },
      {
        "name": "empty",
        "time": "207"
      },
      {
        "name": "markdown",
        "args": [
          {
            "k": "body",
            "t": "str",
            "m": "len:4",
            "p": 1
          },
          {
            "k": "unsafe_allow_html",
            "t": "bool",
            "m": "val:True"
          }
        ],
        "time": "443"
      },
      {
        "name": "plotly_chart",
        "args": [
          {
            "k": "figure_or_data",
            "t": "PlotlyFigure",
            "p": 1
          },
          {
            "k": "use_container_width",
            "t": "bool",
            "m": "val:True"
          }
        ],
        "time": "2816"
      },
      {
        "name": "expander",
        "args": [
          {
            "k": "label",
            "t": "str",
            "m": "len:12",
            "p": 1
          }
        ],
        "time": "250"
      },
      {
        "name": "form",
        "args": [
          {
            "k": "key",
            "t": "str",
            "m": "len:12",
            "p": 1
          }
        ],
        "time": "229"
      },
      {
        "name": "text_input",
        "args": [
          {
            "k": "label",
            "t": "str",
            "m": "len:72",
            "p": 1
          }
        ],
        "time": "390"
      },
      {
        "name": "form_submit_button",
        "args": [
          {
            "k": "label",
            "t": "str",
            "m": "len:6",
            "p": 1
          }
        ],
        "time": "308"
      },
      {
        "name": "divider",
        "time": "194"
      },
      {
        "name": "write",
        "args": [
          {
            "k": "1",
            "t": "str",
            "m": "len:104",
            "p": 1
          }
        ],
        "time": "260"
      }
    ],
    "execTime": "8700177",
    "prepTime": "705",
    "config": [
      "global.showWarningOnDirectExecution",
      "theme.font",
      "client.showErrorDetails",
      "theme.backgroundColor",
      "theme.secondaryBackgroundColor",
      "theme.textColor",
      "server.address",
      "server.port:default",
      "theme.dataframeHeaderBackgroundColor",
      "theme.base",
      "theme.primaryColor",
      "client.toolbarMode",
      "ui.hideTopBar"
    ],
    "attributions": [
      "pydantic",
      "psycopg2",
      "authlib",
      "streamlit_extras",
      "pymongo",
      "sqlite3"
    ],
    "os": "linux",
    "timezone": "('UTC', 'UTC')",
    "headless": true
  }
}